{"rating": "7.8", "maleLinks": [{"source": "u4578", "counts": 8, "lines": [{"themes": [0, 1, 0, 0, 0, 1, 0, 0, 0, 1, 1], "dialogues": [{"uttered": "u4578", "characterName": "DMITRI", "lineId": "L140543", "sentiment": 0.4, "text": "I see.  That was an important list, wouldn't you say?  The people on that list are being subpoenaed tomorrow by a federal judge.  And you \"lost\" it?"}, {"uttered": "u4584", "characterName": "MAX", "lineId": "L140544", "sentiment": -0.5, "text": "I'm sorry."}, {"uttered": "u4578", "characterName": "DMITRI", "lineId": "L140545", "sentiment": -0.5, "text": "Sorry?"}], "sentiment": -0.2}, {"themes": [0, 0, 1, 0, 1, 0, 0, 0, 0, 0, 1], "dialogues": [{"uttered": "u4578", "characterName": "DMITRI", "lineId": "L140546", "sentiment": 0.0, "text": "Tell me, Vincent.  Do you believe in Santa Claus?"}, {"uttered": "u4584", "characterName": "MAX", "lineId": "L140547", "sentiment": 0.0, "text": "Can't say that I do."}, {"uttered": "u4578", "characterName": "DMITRI", "lineId": "L140548", "sentiment": -0.039259259, "text": "Neither do I.  But my children, they're still young.  Do you know who they like even more than jolly old Saint Nicholas?  His helper, Black Peter. An old Russian fairy tale tells of how Santa got so busy looking after all the good kids, he had to hire a helper to punish all the bad kids.  That was Black Peter's job.  He was given the list of all the bad children, and he would visit them in their homes late at night.  And if he caught them not saying their prayers, he would leave a bundle of wooden switches outside their door.  That was a warning.  If they continued to misbehave, he would swoop down and take the children away. And they would never be seen again."}], "sentiment": -0.039259259}, {"themes": [0, 0, 0, 0, 0, 0, 0, 1, 0, 0, 1], "dialogues": [{"uttered": "u4578", "characterName": "DMITRI", "lineId": "L140550", "sentiment": 0.0, "text": "Tell me Vincent.  Tell me what you think."}, {"uttered": "u4584", "characterName": "MAX", "lineId": "L140551", "sentiment": 0.0, "text": "I think..."}], "sentiment": 0.0}, {"themes": [0, 0, 0, 0, 0, 0, 0, 1, 0, 1, 0], "dialogues": [{"uttered": "u4578", "characterName": "DMITRI", "lineId": "L140552", "sentiment": 0.0, "text": "What?"}, {"uttered": "u4584", "characterName": "MAX", "lineId": "L140553", "sentiment": -0.6, "text": "I think...  ...I think you should get this gun out of my fucking face."}, {"uttered": "u4578", "characterName": "DMITRI", "lineId": "L140554", "sentiment": 0.0, "text": "What?  What did you say?"}, {"uttered": "u4584", "characterName": "MAX", "lineId": "L140555", "sentiment": -0.6, "text": "I said.  Get the gun.  Out.  Of my fucking <u>face.</u> Before I wrap it in a blintz and feed it to you."}], "sentiment": -0.6}, {"themes": [0, 0, 0, 0, 0, 0, 0, 1, 0, 0, 0], "dialogues": [{"uttered": "u4584", "characterName": "MAX", "lineId": "L140556", "sentiment": 0.0, "text": "I picked up a tail."}, {"uttered": "u4578", "characterName": "DMITRI", "lineId": "L140557", "sentiment": 0.0, "text": "Federal?"}, {"uttered": "u4584", "characterName": "MAX", "lineId": "L140558", "sentiment": -0.295833333, "text": "You tell me.  I had to toss the list in the river.  I was protecting your sorry, long-winded ass.  So why don't you show a little courtesy?"}], "sentiment": -0.295833333}, {"themes": [0, 0, 0, 0, 0, 0, 0, 0, 0, 0, 0], "dialogues": [{"uttered": "u4584", "characterName": "MAX", "lineId": "L140559", "sentiment": -0.5, "text": "You think I wanted to come here tonight?  You think I'm that stupid? Sometimes shit happens, you gotta roll with it."}, {"uttered": "u4578", "characterName": "DMITRI", "lineId": "L140560", "sentiment": -0.355555556, "text": "Tell me.  Has Black Peter already crossed off a few bad children?"}, {"uttered": "u4584", "characterName": "MAX", "lineId": "L140561", "sentiment": -0.125, "text": "The fat man on Cherry Street.  The other fat man, Mr. Bulldozer.  The trumpet player.  That leaves two."}, {"uttered": "u4578", "characterName": "DMITRI", "lineId": "L140562", "sentiment": 0.0, "text": "Can you finish on schedule?"}, {"uttered": "u4584", "characterName": "MAX", "lineId": "L140563", "sentiment": 0.0, "text": "In fifteen years, I have never left a customer unsatisfied."}], "sentiment": -0.313095238}, {"themes": [0, 0, 0, 0, 1, 0, 0, 0, 0, 0, 0], "dialogues": [{"uttered": "u4578", "characterName": "DMITRI", "lineId": "L140570", "sentiment": 0.0, "text": "Vincent.  Do not cross me."}, {"uttered": "u4584", "characterName": "MAX", "lineId": "L140571", "sentiment": 0.0, "text": "Wouldn't dream of it."}], "sentiment": 0.0}, {"themes": [0, 0, 0, 0, 1, 0, 0, 0, 0, 0, 0], "dialogues": [{"uttered": "u4584", "characterName": "MAX", "lineId": "L140572", "sentiment": 0.0, "text": "As a token of my appreciation for your understanding in this matter, I'd like to offer you a discount for my services tonight.  Twenty five percent."}, {"uttered": "u4578", "characterName": "DMITRI", "lineId": "L140573", "sentiment": 0.0, "text": "Twenty five?"}, {"uttered": "u4584", "characterName": "MAX", "lineId": "L140574", "sentiment": 0.0, "text": "Hell, make it fifty.  Same goes for any business we have in the future."}, {"uttered": "u4578", "characterName": "DMITRI", "lineId": "L140575", "sentiment": 0.2, "text": "Very generous."}, {"uttered": "u4584", "characterName": "MAX", "lineId": "L140576", "sentiment": -0.5, "text": "By the way.  Daniel said he was sorry."}], "sentiment": -0.075}], "target": "u4584"}, {"source": "u4584", "counts": 69, "lines": [{"themes": [1, 0, 0, 0, 1, 0, 0, 0, 0, 0, 0], "dialogues": [{"uttered": "u4587", "characterName": "VINCENT", "lineId": "L140029", "sentiment": 0.0, "text": "Hello?"}, {"uttered": "u4584", "characterName": "MAX", "lineId": "L140030", "sentiment": -0.5, "text": "Oh.  Sorry."}], "sentiment": -0.5}, {"themes": [0, 0, 0, 0, 1, 0, 0, 1, 0, 0, 0], "dialogues": [{"uttered": "u4587", "characterName": "VINCENT", "lineId": "L140031", "sentiment": 0.0, "text": "Uh, let's go to...  Hello...?"}, {"uttered": "u4584", "characterName": "MAX", "lineId": "L140032", "sentiment": -0.5, "text": "Yeah, yeah, sorry..."}], "sentiment": -0.5}, {"themes": [0, 0, 0, 0, 0, 0, 0, 0, 0, 0, 0], "dialogues": [{"uttered": "u4587", "characterName": "VINCENT", "lineId": "L140037", "sentiment": -0.05, "text": "How long you think this'll take?"}, {"uttered": "u4584", "characterName": "MAX", "lineId": "L140038", "sentiment": 0.0, "text": "Twenty-four minutes."}, {"uttered": "u4587", "characterName": "VINCENT", "lineId": "L140039", "sentiment": 0.0, "text": "Twenty-four?  Not twenty-five?  Or twenty-three?"}, {"uttered": "u4584", "characterName": "MAX", "lineId": "L140040", "sentiment": 0.1, "text": "Two minutes to get on Broadway. They're doing some roadwork around the bridge.  Eleven to get downtown.  Four to the Lower East Side.  Six to clear the roadwork.  One minute margin for error.  My math says twenty-four."}], "sentiment": 0.025}, {"themes": [0, 0, 0, 0, 1, 1, 0, 0, 0, 0, 0], "dialogues": [{"uttered": "u4587", "characterName": "VINCENT", "lineId": "L140041", "sentiment": -0.05, "text": "Mind if I time you?  What do I get if you're wrong?  A free ride?"}, {"uttered": "u4584", "characterName": "MAX", "lineId": "L140042", "sentiment": 0.0, "text": "An apology."}], "sentiment": -0.05}, {"themes": [0, 0, 0, 0, 1, 0, 0, 1, 0, 0, 0], "dialogues": [{"uttered": "u4584", "characterName": "MAX", "lineId": "L140043", "sentiment": 0.193181818, "text": "First time in New York?"}, {"uttered": "u4587", "characterName": "VINCENT", "lineId": "L140044", "sentiment": 0.1, "text": "Third, but I still can't tell uptown from downtown.  Tell the truth, whenever I'm here, I can't wait to leave.  Place gets to me.  Too loud, too fast...too much.  You like it here?"}, {"uttered": "u4584", "characterName": "MAX", "lineId": "L140045", "sentiment": 0.0, "text": "It's home."}, {"uttered": "u4587", "characterName": "VINCENT", "lineId": "L140046", "sentiment": 0.144545455, "text": "You share it with over three million people every day.  You know that's the population of New Zealand?  What's Manhattan, thirteen miles long? That's a lot of misery crammed into thirteen miles.  Read about this one guy.  Gets on the subway and dies.  Six hours he's riding around before anybody notices. Think about that.  Here's this corpse doing laps around Manhattan courtesy of the New York transit system, people getting on and off, sitting next to him, and still nobody catches on. Three million.  That's too damn many people."}, {"uttered": "u4584", "characterName": "MAX", "lineId": "L140047", "sentiment": 0.0, "text": "I see your point."}], "sentiment": 0.140909091}, {"themes": [0, 0, 0, 0, 1, 1, 0, 1, 0, 1, 0], "dialogues": [{"uttered": "u4587", "characterName": "VINCENT", "lineId": "L140048", "sentiment": 0.0, "text": "You know, this is the cleanest cab I've ever been in.  This your regular ride?"}, {"uttered": "u4584", "characterName": "MAX", "lineId": "L140049", "sentiment": 0.0, "text": "Yeah.  I share it with the dayshift guy."}, {"uttered": "u4587", "characterName": "VINCENT", "lineId": "L140050", "sentiment": 0.0, "text": "You prefer nights?"}, {"uttered": "u4584", "characterName": "MAX", "lineId": "L140051", "sentiment": 0.166666667, "text": "People are more relaxed.  Less stress, less traffic, better tips."}, {"uttered": "u4587", "characterName": "VINCENT", "lineId": "L140052", "sentiment": 0.6, "text": "You on some kind of work plan?"}, {"uttered": "u4584", "characterName": "MAX", "lineId": "L140053", "sentiment": -0.3125, "text": "You mean like benefits?"}, {"uttered": "u4587", "characterName": "VINCENT", "lineId": "L140054", "sentiment": -0.714285714, "text": "Yeah.  Retirement?  Paid sick leave?"}, {"uttered": "u4584", "characterName": "MAX", "lineId": "L140055", "sentiment": 0.6, "text": "It's not that kind of job."}, {"uttered": "u4587", "characterName": "VINCENT", "lineId": "L140056", "sentiment": 0.0, "text": "You should start a union."}, {"uttered": "u4584", "characterName": "MAX", "lineId": "L140057", "sentiment": 0.0, "text": "Me, specifically?"}, {"uttered": "u4587", "characterName": "VINCENT", "lineId": "L140058", "sentiment": 0.0, "text": "Why not?"}, {"uttered": "u4584", "characterName": "MAX", "lineId": "L140059", "sentiment": 0.0, "text": "Last thing I need is a reason to keep hacking.  This job's a fill-in."}, {"uttered": "u4587", "characterName": "VINCENT", "lineId": "L140060", "sentiment": -0.05, "text": "Oh?  How long you been doing this?"}, {"uttered": "u4584", "characterName": "MAX", "lineId": "L140061", "sentiment": -0.125, "text": "Twelve years.  But I'm working on other stuff..."}, {"uttered": "u4587", "characterName": "VINCENT", "lineId": "L140062", "sentiment": 0.0, "text": "Like what?"}, {"uttered": "u4584", "characterName": "MAX", "lineId": "L140063", "sentiment": 0.0, "text": "I don't talk about it, you know...  No offense."}, {"uttered": "u4587", "characterName": "VINCENT", "lineId": "L140064", "sentiment": 0.0, "text": "None taken.  There are talkers and doers.  I like doers."}], "sentiment": 0.055406746}, {"themes": [0, 1, 0, 0, 0, 1, 0, 0, 0, 1, 0], "dialogues": [{"uttered": "u4587", "characterName": "VINCENT", "lineId": "L140065", "sentiment": 0.25, "text": "Twenty-four minutes!  Man, you're hot..."}, {"uttered": "u4584", "characterName": "MAX", "lineId": "L140066", "sentiment": 0.333333333, "text": "Yeah.  Lucky with the lights."}, {"uttered": "u4587", "characterName": "VINCENT", "lineId": "L140067", "sentiment": 0.4, "text": "Bullshit.  You probably know the light schedules, too.  Listen, I'm in town tonight on a closing.  Five stops, one night.  I gotta catch a six a.m. flight.  I got five stops to make, see some friends, collect some signatures.  Why don't you hang with me?"}, {"uttered": "u4584", "characterName": "MAX", "lineId": "L140068", "sentiment": 0.0, "text": "I'm not a hire car.  It's against regs?"}, {"uttered": "u4587", "characterName": "VINCENT", "lineId": "L140069", "sentiment": 0.007539683, "text": "Regulations?  These guys don't even give you sick leave.  How much you pull down on a good night?"}, {"uttered": "u4584", "characterName": "MAX", "lineId": "L140070", "sentiment": 0.0, "text": "Two, two-fifty."}, {"uttered": "u4587", "characterName": "VINCENT", "lineId": "L140071", "sentiment": 0.0, "text": "I'll make it an even five hundred. Plus an extra hundred if you get me to LAX on time."}], "sentiment": 0.126686508}, {"themes": [0, 1, 0, 1, 0, 0, 0, 0, 0, 0, 1], "dialogues": [{"uttered": "u4587", "characterName": "VINCENT", "lineId": "L140073", "sentiment": 0.0, "text": "We have a deal.  What's your name?"}, {"uttered": "u4584", "characterName": "MAX", "lineId": "L140074", "sentiment": 0.0, "text": "Max."}, {"uttered": "u4587", "characterName": "VINCENT", "lineId": "L140075", "sentiment": 0.0, "text": "Max?  I'm Vincent."}], "sentiment": 0.0}, {"themes": [0, 0, 0, 0, 1, 0, 0, 0, 0, 0, 0], "dialogues": [{"uttered": "u4584", "characterName": "MAX", "lineId": "L140078", "sentiment": 0.0, "text": "He fell on my cab!  From up th-th-there."}, {"uttered": "u4587", "characterName": "VINCENT", "lineId": "L140079", "sentiment": 0.0, "text": "You always stutter?"}, {"uttered": "u4584", "characterName": "MAX", "lineId": "L140080", "sentiment": -0.2, "text": "Yeah, yeah.  Shit, man.  Guy fell on my motherfucking cab."}], "sentiment": -0.2}, {"themes": [0, 1, 0, 0, 0, 0, 0, 0, 0, 0, 0], "dialogues": [{"uttered": "u4584", "characterName": "MAX", "lineId": "L140081", "sentiment": -0.2, "text": "I think he's dead."}, {"uttered": "u4587", "characterName": "VINCENT", "lineId": "L140082", "sentiment": 0.05, "text": "No shit.  Since he has two .45s double- tapped through the sternum and fell six floors onto his head..."}], "sentiment": -0.033333333}, {"themes": [0, 1, 0, 0, 0, 0, 0, 0, 1, 1, 0], "dialogues": [{"uttered": "u4584", "characterName": "MAX", "lineId": "L140083", "sentiment": -0.2, "text": "You - you killed him?"}, {"uttered": "u4587", "characterName": "VINCENT", "lineId": "L140084", "sentiment": -0.2, "text": "No-no, I-I shot him.  The bullets and the fall killed him."}], "sentiment": -0.2}, {"themes": [1, 0, 0, 0, 1, 0, 0, 0, 0, 1, 0], "dialogues": [{"uttered": "u4587", "characterName": "VINCENT", "lineId": "L140087", "sentiment": 0.35, "text": "You cool, Max?  Say \"I'm cool.\""}, {"uttered": "u4584", "characterName": "MAX", "lineId": "L140088", "sentiment": 0.35, "text": "You're cool."}, {"uttered": "u4587", "characterName": "VINCENT", "lineId": "L140089", "sentiment": 0.35, "text": "No.  You say you're cool."}, {"uttered": "u4584", "characterName": "MAX", "lineId": "L140090", "sentiment": 0.35, "text": "I'm cool."}], "sentiment": 0.35}, {"themes": [1, 1, 0, 0, 1, 1, 1, 1, 0, 1, 0], "dialogues": [{"uttered": "u4587", "characterName": "VINCENT", "lineId": "L140091", "sentiment": 0.7, "text": "Good.  Help me out here."}, {"uttered": "u4584", "characterName": "MAX", "lineId": "L140092", "sentiment": 0.0, "text": "With what?"}, {"uttered": "u4587", "characterName": "VINCENT", "lineId": "L140093", "sentiment": 0.0, "text": "You were going to drive me around. Drop me at LAX.  Never be the wiser. But El Gordo missed the elevator.  So we go to Plan B.  Pop the trunk."}, {"uttered": "u4584", "characterName": "MAX", "lineId": "L140094", "sentiment": 0.0, "text": "The trunk?"}, {"uttered": "u4587", "characterName": "VINCENT", "lineId": "L140095", "sentiment": 0.0, "text": "Did I stutter?  The trunk.  Unless you want him riding up front with you...but given hygiene and his sphincters have let go..."}], "sentiment": 0.7}, {"themes": [0, 1, 0, 0, 1, 0, 0, 1, 0, 1, 0], "dialogues": [{"uttered": "u4587", "characterName": "VINCENT", "lineId": "L140096", "sentiment": 0.0, "text": "I'm gonna roll him off the hood. Always lift with your legs..."}, {"uttered": "u4584", "characterName": "MAX", "lineId": "L140097", "sentiment": 0.0, "text": "I don't think I can do this."}, {"uttered": "u4587", "characterName": "VINCENT", "lineId": "L140098", "sentiment": 0.0, "text": "It's just a dead guy.  On three, ready?  Uno.  Dos.  Three."}], "sentiment": 0.0}, {"themes": [0, 1, 0, 0, 0, 0, 0, 0, 0, 1, 0], "dialogues": [{"uttered": "u4587", "characterName": "VINCENT", "lineId": "L140099", "sentiment": 0.0, "text": "Got it?"}, {"uttered": "u4584", "characterName": "MAX", "lineId": "L140100", "sentiment": 0.0, "text": "Yeah."}], "sentiment": 0.0}, {"themes": [0, 1, 0, 0, 1, 1, 0, 0, 0, 1, 0], "dialogues": [{"uttered": "u4587", "characterName": "VINCENT", "lineId": "L140101", "sentiment": 0.0, "text": "What?"}, {"uttered": "u4584", "characterName": "MAX", "lineId": "L140102", "sentiment": 0.0, "text": "His hand moved!  His goddamn hand twitched!"}, {"uttered": "u4587", "characterName": "VINCENT", "lineId": "L140103", "sentiment": 0.0, "text": "It's a spasm!  Jesus, Max, don't be such a girl..."}], "sentiment": 0.0}, {"themes": [0, 0, 1, 0, 0, 0, 0, 0, 0, 1, 0], "dialogues": [{"uttered": "u4584", "characterName": "MAX", "lineId": "L140106", "sentiment": 0.0, "text": "Uh, look...why don't you just take the car..."}, {"uttered": "u4587", "characterName": "VINCENT", "lineId": "L140107", "sentiment": -0.157142857, "text": "...and you promise you'll never tell anybody about this, right?  Get in the fucking car."}], "sentiment": -0.157142857}, {"themes": [0, 0, 0, 0, 0, 0, 0, 0, 0, 0, 0], "dialogues": [{"uttered": "u4587", "characterName": "VINCENT", "lineId": "L140109", "sentiment": 0.0, "text": "Max.  May we leave the scene of the crime now, please."}, {"uttered": "u4584", "characterName": "MAX", "lineId": "L140110", "sentiment": 0.0, "text": "I'm trying..."}], "sentiment": 0.0}, {"themes": [0, 0, 1, 0, 1, 0, 0, 0, 0, 0, 0], "dialogues": [{"uttered": "u4587", "characterName": "VINCENT", "lineId": "L140111", "sentiment": 0.0, "text": "Max."}, {"uttered": "u4584", "characterName": "MAX", "lineId": "L140112", "sentiment": 0.0, "text": "It's not me."}], "sentiment": 0.0}, {"themes": [0, 0, 0, 0, 0, 1, 0, 0, 0, 1, 0], "dialogues": [{"uttered": "u4587", "characterName": "VINCENT", "lineId": "L140114", "sentiment": 0.0, "text": "You listening to me?"}, {"uttered": "u4584", "characterName": "MAX", "lineId": "L140115", "sentiment": 0.0, "text": "Yes!  I'm trying, I swear!"}, {"uttered": "u4587", "characterName": "VINCENT", "lineId": "L140116", "sentiment": -0.1, "text": "Try harder.  I'm gonna count to three. One..."}, {"uttered": "u4587", "characterName": "VINCENT", "lineId": "L140117", "sentiment": 0.0, "text": "Two..."}, {"uttered": "u4584", "characterName": "MAX", "lineId": "L140118", "sentiment": 0.0, "text": "It's not me, it's the engine!  A fat guy fell on it from six floors up!"}], "sentiment": -0.15625}, {"themes": [1, 0, 0, 0, 0, 1, 0, 0, 1, 0, 0], "dialogues": [{"uttered": "u4587", "characterName": "VINCENT", "lineId": "L140119", "sentiment": 0.0, "text": "What about that?"}, {"uttered": "u4584", "characterName": "MAX", "lineId": "L140120", "sentiment": 0.0, "text": "I tried it."}, {"uttered": "u4587", "characterName": "VINCENT", "lineId": "L140121", "sentiment": 0.0, "text": "How about the thingy next to it?"}, {"uttered": "u4584", "characterName": "MAX", "lineId": "L140122", "sentiment": 0.0, "text": "The thingy next to it has nothing to do with the starter motor..."}, {"uttered": "u4587", "characterName": "VINCENT", "lineId": "L140123", "sentiment": 0.0, "text": "I'm making <u>you</u> nervous.  I'm the one with a schedule."}, {"uttered": "u4584", "characterName": "MAX", "lineId": "L140124", "sentiment": 0.5, "text": "Okay, try it now."}], "sentiment": 0.166666667}, {"themes": [0, 0, 0, 0, 0, 1, 0, 0, 0, 0, 0], "dialogues": [{"uttered": "u4587", "characterName": "VINCENT", "lineId": "L140127", "sentiment": 0.0, "text": "Try some deep breathing."}, {"uttered": "u4584", "characterName": "MAX", "lineId": "L140128", "sentiment": 0.0, "text": "What?"}, {"uttered": "u4587", "characterName": "VINCENT", "lineId": "L140129", "sentiment": -0.244444444, "text": "Adrenaline's wearing off.  You get shaky after.  It's not uncommon.  Deep breathing helps."}], "sentiment": -0.183333333}, {"themes": [0, 0, 0, 0, 0, 0, 0, 0, 0, 0, 0], "dialogues": [{"uttered": "u4587", "characterName": "VINCENT", "lineId": "L140130", "sentiment": 0.5, "text": "You better?"}, {"uttered": "u4584", "characterName": "MAX", "lineId": "L140131", "sentiment": 0.0, "text": "I think so."}], "sentiment": 0.5}, {"themes": [0, 0, 0, 0, 0, 1, 0, 0, 0, 0, 0], "dialogues": [{"uttered": "u4587", "characterName": "VINCENT", "lineId": "L140132", "sentiment": 0.0, "text": "What are you doing?"}, {"uttered": "u4584", "characterName": "MAX", "lineId": "L140133", "sentiment": -0.175, "text": "It's a mess."}, {"uttered": "u4587", "characterName": "VINCENT", "lineId": "L140134", "sentiment": 0.0, "text": "So?"}], "sentiment": -0.175}, {"themes": [1, 0, 0, 0, 0, 0, 0, 0, 0, 0, 0], "dialogues": [{"uttered": "u4587", "characterName": "VINCENT", "lineId": "L140138", "sentiment": 0.0, "text": "58th and Central.  You know it?"}, {"uttered": "u4584", "characterName": "MAX", "lineId": "L140139", "sentiment": 0.0, "text": "South Central."}, {"uttered": "u4587", "characterName": "VINCENT", "lineId": "L140140", "sentiment": -0.05, "text": "How long, you figure?"}], "sentiment": -0.016666667}, {"themes": [0, 0, 1, 0, 0, 0, 0, 0, 0, 0, 0], "dialogues": [{"uttered": "u4584", "characterName": "MAX", "lineId": "L140142", "sentiment": 0.0, "text": "Oh.  Oh, no.  You're kidding.  We..."}, {"uttered": "u4587", "characterName": "VINCENT", "lineId": "L140143", "sentiment": -0.125, "text": "I told you we had other stops to make tonight."}, {"uttered": "u4584", "characterName": "MAX", "lineId": "L140144", "sentiment": 0.0, "text": "You said you were visiting friends!"}, {"uttered": "u4587", "characterName": "VINCENT", "lineId": "L140145", "sentiment": 0.285714286, "text": "They're <u>somebody's</u> friends...  You drive a cab.  I kill people.  We both do our jobs right, you might survive the night and come out four hundred bucks ahead."}, {"uttered": "u4584", "characterName": "MAX", "lineId": "L140146", "sentiment": 0.5, "text": "Listen.  I'm not trying to piss you off, see?  Okay?  I can't drive you around so you can murder folks."}, {"uttered": "u4587", "characterName": "VINCENT", "lineId": "L140147", "sentiment": 0.0, "text": "Tonight it is."}, {"uttered": "u4584", "characterName": "MAX", "lineId": "L140148", "sentiment": -0.20625, "text": "You don't understand.  I mean it. Really.  I'm not up for this..."}], "sentiment": 0.043392857}, {"themes": [0, 0, 0, 0, 0, 0, 0, 0, 0, 0, 0], "dialogues": [{"uttered": "u4587", "characterName": "VINCENT", "lineId": "L140150", "sentiment": 0.0, "text": "Are you breathing?"}, {"uttered": "u4584", "characterName": "MAX", "lineId": "L140151", "sentiment": 0.0, "text": "Yes."}, {"uttered": "u4587", "characterName": "VINCENT", "lineId": "L140152", "sentiment": -0.155555556, "text": "What else calms you down?  Candy? Cigarettes?  Sex?  Breathe."}], "sentiment": -0.155555556}, {"themes": [0, 0, 0, 0, 0, 0, 0, 0, 0, 0, 0], "dialogues": [{"uttered": "u4584", "characterName": "MAX", "lineId": "L140153", "sentiment": 0.0, "text": "Music."}, {"uttered": "u4587", "characterName": "VINCENT", "lineId": "L140154", "sentiment": 0.0, "text": "Play music."}], "sentiment": 0.0}, {"themes": [0, 1, 1, 0, 0, 0, 1, 0, 0, 1, 0], "dialogues": [{"uttered": "u4587", "characterName": "VINCENT", "lineId": "L140155", "sentiment": 0.466666667, "text": "Chopin prelude.  Stodgy, but nice.  Here's the deal.  I didn't want you involved in this.  Still breathing? But now that you are, we have to make the best of it, Max.  Improvise.  Life is that way.  Adapt to your environment.  Survive.  Darwin.  \"Shit happens.\"  The I Ching.  Whatever. Roll with it."}, {"uttered": "u4584", "characterName": "MAX", "lineId": "L140156", "sentiment": 0.0, "text": "I Ching?  You threw a man out a window!"}, {"uttered": "u4587", "characterName": "VINCENT", "lineId": "L140157", "sentiment": 0.0, "text": "I didn't throw him, he fell."}, {"uttered": "u4584", "characterName": "MAX", "lineId": "L140158", "sentiment": 0.0, "text": "What'd he do to you?"}, {"uttered": "u4587", "characterName": "VINCENT", "lineId": "L140159", "sentiment": 0.0, "text": "Nothing.  I only met him the one time."}, {"uttered": "u4584", "characterName": "MAX", "lineId": "L140160", "sentiment": 0.0, "text": "How can you kill him like that?"}, {"uttered": "u4587", "characterName": "VINCENT", "lineId": "L140161", "sentiment": 0.0, "text": "I should only kill people after I get to know 'em?  Six billion people on the planet, you're getting bent out of shape 'cause of one fat guy?"}, {"uttered": "u4584", "characterName": "MAX", "lineId": "L140162", "sentiment": 0.0, "text": "Who was he?"}, {"uttered": "u4587", "characterName": "VINCENT", "lineId": "L140163", "sentiment": 0.0, "text": "What do you care?  Ever hear of Rwanda?"}, {"uttered": "u4584", "characterName": "MAX", "lineId": "L140164", "sentiment": 0.0, "text": "Rwanda-Burundi.  Central Africa."}, {"uttered": "u4587", "characterName": "VINCENT", "lineId": "L140165", "sentiment": 0.04, "text": "Tens of thousands killed before sundown.  Nobody's killed that fast since Hiroshima and Nagasaki.  Did you bat an eye, Max?  Join Amnesty International?  No.  I off one Angeleno, you throw a hissy fit..."}], "sentiment": 0.140909091}, {"themes": [0, 0, 0, 0, 0, 0, 0, 0, 0, 0, 0], "dialogues": [{"uttered": "u4584", "characterName": "MAX", "lineId": "L140166", "sentiment": 0.0, "text": "I don't know any Rwandans."}, {"uttered": "u4587", "characterName": "VINCENT", "lineId": "L140167", "sentiment": 0.05, "text": "You don't know the guy in the trunk, either.  If it makes you feel better, he was a villain involved in a Continuing Criminal Enterprise."}, {"uttered": "u4584", "characterName": "MAX", "lineId": "L140168", "sentiment": 0.5, "text": "Oh, it's okay, then.  'Cause you're just taking out the garbage..."}, {"uttered": "u4587", "characterName": "VINCENT", "lineId": "L140169", "sentiment": 0.05, "text": "Yeah, like that...  But, anyway, nobody gets out of this alive.  Even if we quit smoking and cut out red meat.  Everybody dies."}], "sentiment": 0.14}, {"themes": [0, 1, 0, 0, 0, 0, 0, 0, 0, 1, 0], "dialogues": [{"uttered": "u4587", "characterName": "VINCENT", "lineId": "L140170", "sentiment": 0.0, "text": "Get rid of 'em."}, {"uttered": "u4584", "characterName": "MAX", "lineId": "L140171", "sentiment": 0.0, "text": "How?"}, {"uttered": "u4587", "characterName": "VINCENT", "lineId": "L140172", "sentiment": 0.0, "text": "You're a cabby.  Like talk yourself out of a ticket?"}], "sentiment": 0.0}, {"themes": [0, 0, 0, 0, 0, 0, 0, 1, 0, 1, 0], "dialogues": [{"uttered": "u4584", "characterName": "MAX", "lineId": "L140173", "sentiment": 0.0, "text": "Please.  Don't do anything."}, {"uttered": "u4587", "characterName": "VINCENT", "lineId": "L140174", "sentiment": 0.0, "text": "Then don't let me get cornered, Max. You don't have the trunk space."}, {"uttered": "u4584", "characterName": "MAX", "lineId": "L140175", "sentiment": 0.0, "text": "I can't believe this."}, {"uttered": "u4587", "characterName": "VINCENT", "lineId": "L140176", "sentiment": 0.0, "text": "Believe it."}], "sentiment": 0.0}, {"themes": [0, 0, 0, 0, 0, 0, 0, 0, 0, 0, 0], "dialogues": [{"uttered": "u4584", "characterName": "MAX", "lineId": "L140177", "sentiment": 0.0, "text": "I'll talk to them, I'll talk to them."}, {"uttered": "u4587", "characterName": "VINCENT", "lineId": "L140178", "sentiment": 0.7, "text": "Good luck.  You think they got families?"}], "sentiment": 0.7}, {"themes": [0, 1, 1, 0, 1, 0, 0, 0, 0, 1, 0], "dialogues": [{"uttered": "u4587", "characterName": "VINCENT", "lineId": "L140179", "sentiment": 0.291666667, "text": "That one's probably married.  Think of his kids.  His wife's pregnant..."}, {"uttered": "u4584", "characterName": "MAX", "lineId": "L140180", "sentiment": 0.0, "text": "I'll deal with it.  I will, I will..."}], "sentiment": 0.291666667}, {"themes": [0, 0, 0, 0, 0, 0, 0, 0, 0, 0, 0], "dialogues": [{"uttered": "u4587", "characterName": "VINCENT", "lineId": "L140207", "sentiment": 0.0, "text": "Hands on the wheel.  Ten and two o'clock, like they taught you in driver's ed."}, {"uttered": "u4584", "characterName": "MAX", "lineId": "L140208", "sentiment": 0.0, "text": "Why?"}, {"uttered": "u4587", "characterName": "VINCENT", "lineId": "L140209", "sentiment": 0.0, "text": "Because I have a gun and I say so."}], "sentiment": 0.0}, {"themes": [0, 1, 0, 0, 1, 0, 0, 0, 0, 1, 0], "dialogues": [{"uttered": "u4587", "characterName": "VINCENT", "lineId": "L140212", "sentiment": 0.0, "text": "Who's that?"}, {"uttered": "u4584", "characterName": "MAX", "lineId": "L140213", "sentiment": 0.0, "text": "Lenny, my dispatcher."}], "sentiment": 0.0}, {"themes": [0, 0, 0, 0, 0, 0, 0, 0, 0, 0, 0], "dialogues": [{"uttered": "u4587", "characterName": "VINCENT", "lineId": "L140225", "sentiment": 0.05, "text": "It was an accident.  You're not liable.  Tell him."}, {"uttered": "u4584", "characterName": "MAX", "lineId": "L140226", "sentiment": 0.05, "text": "It was an accident.  I'm not liable."}], "sentiment": 0.05}, {"themes": [1, 1, 0, 0, 0, 0, 0, 0, 0, 1, 0], "dialogues": [{"uttered": "u4587", "characterName": "VINCENT", "lineId": "L140228", "sentiment": -0.4, "text": "Don't take that.  Tell him to shut the fuck up."}, {"uttered": "u4584", "characterName": "MAX", "lineId": "L140229", "sentiment": 0.0, "text": "I can't do that.  He's the Man.  He'll fire my ass."}, {"uttered": "u4587", "characterName": "VINCENT", "lineId": "L140230", "sentiment": 0.0, "text": "So what?"}, {"uttered": "u4584", "characterName": "MAX", "lineId": "L140231", "sentiment": 0.0, "text": "I need the job."}, {"uttered": "u4587", "characterName": "VINCENT", "lineId": "L140232", "sentiment": 0.0, "text": "No you don't."}], "sentiment": -0.4}, {"themes": [0, 0, 0, 0, 0, 0, 0, 0, 0, 0, 0], "dialogues": [{"uttered": "u4584", "characterName": "MAX", "lineId": "L140241", "sentiment": 0.0, "text": "Lenny?  You're an asshole."}, {"uttered": "u4587", "characterName": "VINCENT", "lineId": "L140242", "sentiment": -0.1, "text": "Tell him next time he pulls any shit, you're gonna kick his fat ass."}, {"uttered": "u4584", "characterName": "MAX", "lineId": "L140243", "sentiment": -0.1, "text": "Next time you pull any shit, I'm gonna kick your fat ass."}], "sentiment": -0.1}, {"themes": [1, 0, 0, 0, 0, 0, 0, 0, 0, 1, 0], "dialogues": [{"uttered": "u4587", "characterName": "VINCENT", "lineId": "L140262", "sentiment": 0.0, "text": "I had no idea these cabs came equipped with emergency strobes.  Where's the button?  Under the dash?"}, {"uttered": "u4584", "characterName": "MAX", "lineId": "L140263", "sentiment": 0.0, "text": "Yeah."}], "sentiment": 0.0}, {"themes": [0, 0, 1, 0, 0, 0, 0, 0, 0, 0, 0], "dialogues": [{"uttered": "u4587", "characterName": "VINCENT", "lineId": "L140265", "sentiment": 0.0, "text": "Another collateral."}, {"uttered": "u4584", "characterName": "MAX", "lineId": "L140266", "sentiment": 0.0, "text": "What?"}, {"uttered": "u4587", "characterName": "VINCENT", "lineId": "L140267", "sentiment": 0.0, "text": "Collateral damage."}, {"uttered": "u4584", "characterName": "MAX", "lineId": "L140268", "sentiment": 0.0, "text": "I don't understand..."}, {"uttered": "u4587", "characterName": "VINCENT", "lineId": "L140269", "sentiment": -0.4, "text": "People in the wrong place at the wrong time.  Draws attention, which is something you avoid in my line of work.  And for <u>you?</u> You attract attention, you're gonna get people killed who don't need to be."}], "sentiment": -0.4}, {"themes": [0, 0, 0, 0, 0, 0, 0, 0, 0, 0, 0], "dialogues": [{"uttered": "u4584", "characterName": "MAX", "lineId": "L140270", "sentiment": 0.0, "text": "Vincent?"}, {"uttered": "u4587", "characterName": "VINCENT", "lineId": "L140271", "sentiment": 0.0, "text": "Yes, Max?"}, {"uttered": "u4584", "characterName": "MAX", "lineId": "L140272", "sentiment": 0.0, "text": "Am I collateral?"}], "sentiment": 0.0}, {"themes": [0, 0, 1, 0, 0, 1, 0, 0, 0, 0, 0], "dialogues": [{"uttered": "u4587", "characterName": "VINCENT", "lineId": "L140274", "sentiment": 0.233333333, "text": "But, hey, some good news.  This last one put me way ahead of schedule. We've actually got some time to kill.  Jazz?  You like jazz?"}, {"uttered": "u4584", "characterName": "MAX", "lineId": "L140275", "sentiment": -0.5, "text": "I'm...what?  Sorry?"}, {"uttered": "u4587", "characterName": "VINCENT", "lineId": "L140276", "sentiment": 0.0, "text": "Jazz.  Music."}, {"uttered": "u4584", "characterName": "MAX", "lineId": "L140277", "sentiment": 0.0, "text": "I listen to classical."}, {"uttered": "u4587", "characterName": "VINCENT", "lineId": "L140278", "sentiment": 0.4, "text": "Friend of mine told me about this great place in South Central.  Says it's like the birthplace of West Coast bebop.  Bird.  Dexter Gordon. Thelonious Monk.  Chet Baker.  I'll buy you a drink.  Expand your horizons..."}], "sentiment": 0.142857143}, {"themes": [0, 0, 0, 0, 0, 0, 0, 1, 0, 0, 0], "dialogues": [{"uttered": "u4587", "characterName": "VINCENT", "lineId": "L140307", "sentiment": 0.208333333, "text": "...see now, this has got a little post- war flavor, a little Miles thing happening.  Awesome.  What do you think?"}, {"uttered": "u4584", "characterName": "MAX", "lineId": "L140308", "sentiment": 0.0, "text": "I never learned jazz."}, {"uttered": "u4587", "characterName": "VINCENT", "lineId": "L140309", "sentiment": 0.0, "text": "God, are you always this prosaic?  You don't learn jazz, it's not something you're <u>taught.</u> It's like breathing, like life.  Like us, tonight, taking what comes and going with the flow."}, {"uttered": "u4584", "characterName": "MAX", "lineId": "L140310", "sentiment": 0.0, "text": "That what we're doing?  Flowing?"}, {"uttered": "u4587", "characterName": "VINCENT", "lineId": "L140311", "sentiment": 0.242857143, "text": "Damn right.  Instinct, man.  If you think too much, it doesn't work.  Just listen..."}, {"uttered": "u4584", "characterName": "MAX", "lineId": "L140312", "sentiment": -0.3, "text": "I'm not catching a melody."}, {"uttered": "u4587", "characterName": "VINCENT", "lineId": "L140313", "sentiment": -0.009722222, "text": "That's the point.  You play <u>between</u> the notes, you dance <u>around</u> the structure, you improvise.  Some people know where they're going to be ten years from now.  Same job, same neighbors, same shit over and over.  That's not living.  That's dying a little every day.  Not me, pal.  It's not knowing what's around the corner that makes like worth living.  That's jazz.  That guy up there, he knows what I'm talking about.  Hell, it's the same thing <u>he's</u> talking about, if you just open your ears.  You can hear it in the conversation he's having with that trumpet..."}], "sentiment": 0.048214286}, {"themes": [0, 0, 0, 0, 0, 0, 0, 0, 0, 0, 0], "dialogues": [{"uttered": "u4584", "characterName": "MAX", "lineId": "L140344", "sentiment": 0.0, "text": "Let him go, Vincent."}, {"uttered": "u4587", "characterName": "VINCENT", "lineId": "L140345", "sentiment": 0.0, "text": "You mind?  I'm working here."}, {"uttered": "u4584", "characterName": "MAX", "lineId": "L140346", "sentiment": -0.1875, "text": "You're the one who keeps talking about going with the flow.  You like the man, you like the way he plays.  How about a little jazz, huh?"}, {"uttered": "u4587", "characterName": "VINCENT", "lineId": "L140347", "sentiment": 0.375, "text": "Jazz?  That's funny, coming from you.  Okay, some jazz for the jazz man. How's this?  I'll ask a question."}], "sentiment": 0.1875}, {"themes": [0, 0, 0, 0, 0, 0, 0, 0, 0, 1, 0], "dialogues": [{"uttered": "u4587", "characterName": "VINCENT", "lineId": "L140363", "sentiment": 0.0, "text": "Let's go."}, {"uttered": "u4584", "characterName": "MAX", "lineId": "L140364", "sentiment": 0.0, "text": "No."}, {"uttered": "u4587", "characterName": "VINCENT", "lineId": "L140365", "sentiment": -0.3125, "text": "What you mean, no?"}, {"uttered": "u4584", "characterName": "MAX", "lineId": "L140366", "sentiment": 0.0, "text": "I'm done.  Find another cab."}], "sentiment": -0.3125}, {"themes": [0, 0, 0, 0, 0, 0, 0, 0, 0, 0, 0], "dialogues": [{"uttered": "u4587", "characterName": "VINCENT", "lineId": "L140367", "sentiment": 0.0, "text": "Max?  What are you doing?"}, {"uttered": "u4584", "characterName": "MAX", "lineId": "L140368", "sentiment": 0.0, "text": "Leave me alone."}, {"uttered": "u4587", "characterName": "VINCENT", "lineId": "L140369", "sentiment": 0.0, "text": "Don't even think you're walking away from me."}, {"uttered": "u4584", "characterName": "MAX", "lineId": "L140370", "sentiment": 0.0, "text": "<u>I don't wanna know you!</u>"}], "sentiment": 0.0}, {"themes": [0, 0, 0, 0, 0, 0, 0, 0, 0, 0, 0], "dialogues": [{"uttered": "u4587", "characterName": "VINCENT", "lineId": "L140371", "sentiment": 0.2, "text": "Pull your head out of your ass.  Get your thinking straight.  You wanna die?"}, {"uttered": "u4584", "characterName": "MAX", "lineId": "L140372", "sentiment": -0.75, "text": "I'm collateral anyway, so just fucking do it and stop making me a part of this!"}, {"uttered": "u4587", "characterName": "VINCENT", "lineId": "L140373", "sentiment": 0.0, "text": "Teach him how to talk back, suddenly he can't stop.  I'm not playing."}, {"uttered": "u4584", "characterName": "MAX", "lineId": "L140374", "sentiment": 0.392857143, "text": "Sure?  Like you didn't play him? String him along?  If he had gotten the answer right, would you have let him go?"}], "sentiment": 0.039285714}, {"themes": [0, 0, 0, 0, 0, 0, 0, 0, 0, 0, 0], "dialogues": [{"uttered": "u4587", "characterName": "VINCENT", "lineId": "L140387", "sentiment": 0.0, "text": "Show up for what?"}, {"uttered": "u4584", "characterName": "MAX", "lineId": "L140388", "sentiment": 0.5, "text": "Tell her I can't see her tonight, okay?"}], "sentiment": 0.5}, {"themes": [1, 1, 1, 0, 0, 0, 0, 1, 0, 1, 0], "dialogues": [{"uttered": "u4587", "characterName": "VINCENT", "lineId": "L140390", "sentiment": 0.0, "text": "Show up for <u>what?</u>"}, {"uttered": "u4584", "characterName": "MAX", "lineId": "L140391", "sentiment": 0.0, "text": "She's in the hospital."}, {"uttered": "u4587", "characterName": "VINCENT", "lineId": "L140392", "sentiment": 0.0, "text": "You go every night?"}, {"uttered": "u4584", "characterName": "MAX", "lineId": "L140393", "sentiment": 0.0, "text": "What difference does it make?"}, {"uttered": "u4587", "characterName": "VINCENT", "lineId": "L140394", "sentiment": -0.525, "text": "Guy with a routine goes and breaks it? Provokes attention.  That's bad.  And that's not good..."}, {"uttered": "u4584", "characterName": "MAX", "lineId": "L140395", "sentiment": 0.0, "text": "There's no way I'm taking you to see my mother!"}], "sentiment": -0.56875}, {"themes": [0, 0, 0, 0, 0, 0, 0, 0, 0, 0, 0], "dialogues": [{"uttered": "u4584", "characterName": "MAX", "lineId": "L140434", "sentiment": -0.125, "text": "Mom, Vincent's not interested."}, {"uttered": "u4587", "characterName": "VINCENT", "lineId": "L140435", "sentiment": 0.0, "text": "Oh, I'm captivated."}], "sentiment": -0.125}, {"themes": [0, 1, 0, 0, 0, 0, 0, 0, 1, 0, 1], "dialogues": [{"uttered": "u4587", "characterName": "VINCENT", "lineId": "L140445", "sentiment": 0.5, "text": "You take one more step, I'll kill her."}, {"uttered": "u4584", "characterName": "MAX", "lineId": "L140446", "sentiment": 0.0, "text": "You'd do her a favor."}], "sentiment": 0.5}, {"themes": [0, 0, 0, 0, 0, 0, 0, 0, 0, 0, 0], "dialogues": [{"uttered": "u4587", "characterName": "VINCENT", "lineId": "L140453", "sentiment": -0.4, "text": "What the fuck was <u>that?</u>"}, {"uttered": "u4584", "characterName": "MAX", "lineId": "L140454", "sentiment": 0.0, "text": "Jazz."}], "sentiment": -0.4}, {"themes": [0, 1, 1, 0, 0, 0, 0, 0, 1, 1, 1], "dialogues": [{"uttered": "u4587", "characterName": "VINCENT", "lineId": "L140468", "sentiment": 0.0, "text": "Limos, huh?"}, {"uttered": "u4584", "characterName": "MAX", "lineId": "L140469", "sentiment": 0.0, "text": "Don't start."}, {"uttered": "u4587", "characterName": "VINCENT", "lineId": "L140470", "sentiment": 0.0, "text": "Hey, I'm not the one who's been lying to my mother."}, {"uttered": "u4584", "characterName": "MAX", "lineId": "L140471", "sentiment": 0.35, "text": "She hears what she wants to hear, okay?"}, {"uttered": "u4587", "characterName": "VINCENT", "lineId": "L140472", "sentiment": 0.0, "text": "Maybe so.  Maybe she hears what you tell her."}, {"uttered": "u4584", "characterName": "MAX", "lineId": "L140473", "sentiment": 0.066666667, "text": "Fuck!  Nothing's ever goddamn good enough!  It's always been that way."}, {"uttered": "u4587", "characterName": "VINCENT", "lineId": "L140474", "sentiment": -0.3, "text": "It's cause they don't like their lives, so they project their patterns of negative behavior onto you...  I had a father like that."}, {"uttered": "u4584", "characterName": "MAX", "lineId": "L140475", "sentiment": 0.0, "text": "Yeah?  What happened?"}, {"uttered": "u4587", "characterName": "VINCENT", "lineId": "L140476", "sentiment": -0.5, "text": "He hated everything I did.  Hated me. Got drunk and beat the shit out of me, daily..."}, {"uttered": "u4584", "characterName": "MAX", "lineId": "L140477", "sentiment": 0.0, "text": "What happened?"}, {"uttered": "u4587", "characterName": "VINCENT", "lineId": "L140478", "sentiment": 0.025, "text": "I killed him.  When I was 15.  He was my first.  Nah, wishful thinking.  Liver cancer."}, {"uttered": "u4584", "characterName": "MAX", "lineId": "L140479", "sentiment": -0.5, "text": "I'm sorry."}, {"uttered": "u4587", "characterName": "VINCENT", "lineId": "L140480", "sentiment": 0.0, "text": "Don't be.  I never saw him after I was 15.  Went into the military early.  So all this talk about \"my job's temporary, I got big plans,\" it's all bullshit."}, {"uttered": "u4584", "characterName": "MAX", "lineId": "L140481", "sentiment": 0.0, "text": "It's not bullshit."}, {"uttered": "u4587", "characterName": "VINCENT", "lineId": "L140482", "sentiment": 0.366666667, "text": "What do <u>you</u> call it?  Ten years doesn't sound temporary to me.  I should have known it was bullshit, you're too good at what you do."}, {"uttered": "u4584", "characterName": "MAX", "lineId": "L140483", "sentiment": 0.566666667, "text": "I've always been good.  Ever since I started.  Gave up piano.  Easy money. I'm putting a stake together, get something started.  Go figure it all out..."}, {"uttered": "u4587", "characterName": "VINCENT", "lineId": "L140484", "sentiment": 0.0, "text": "Yeah?  Like what?  Limos?"}, {"uttered": "u4584", "characterName": "MAX", "lineId": "L140485", "sentiment": 0.0, "text": "I told you I don't like to talk about it."}, {"uttered": "u4587", "characterName": "VINCENT", "lineId": "L140486", "sentiment": 0.0, "text": "Well, this big stake's got to be big by now.  When you leaving?"}, {"uttered": "u4584", "characterName": "MAX", "lineId": "L140487", "sentiment": 0.0, "text": "See, I've got bills.  My mother's been dying of the same disease since I was a kid."}, {"uttered": "u4587", "characterName": "VINCENT", "lineId": "L140488", "sentiment": 0.0, "text": "What, no insurance?"}, {"uttered": "u4584", "characterName": "MAX", "lineId": "L140489", "sentiment": 0.0, "text": "Doesn't cover everything."}, {"uttered": "u4587", "characterName": "VINCENT", "lineId": "L140490", "sentiment": 0.383333333, "text": "Good excuse.  How many others you got?"}], "sentiment": 0.036904762}, {"themes": [0, 0, 0, 0, 0, 0, 0, 0, 0, 0, 0], "dialogues": [{"uttered": "u4587", "characterName": "VINCENT", "lineId": "L140492", "sentiment": 0.0, "text": "Gimme your wallet."}, {"uttered": "u4584", "characterName": "MAX", "lineId": "L140493", "sentiment": 0.0, "text": "Why?"}], "sentiment": 0.0}, {"themes": [0, 0, 0, 0, 0, 0, 0, 0, 0, 0, 0], "dialogues": [{"uttered": "u4587", "characterName": "VINCENT", "lineId": "L140494", "sentiment": 0.0, "text": "I'll just hold onto it for you.  In case they check."}, {"uttered": "u4584", "characterName": "MAX", "lineId": "L140495", "sentiment": 0.0, "text": "In case <u>who</u> checks?"}], "sentiment": 0.0}, {"themes": [0, 0, 1, 0, 1, 1, 1, 1, 0, 0, 0], "dialogues": [{"uttered": "u4587", "characterName": "VINCENT", "lineId": "L140496", "sentiment": -0.1875, "text": "Our friends in Little Russia.  Go in and ask for a man named Dmitri."}, {"uttered": "u4584", "characterName": "MAX", "lineId": "L140497", "sentiment": 0.0, "text": "Dmitri?"}, {"uttered": "u4587", "characterName": "VINCENT", "lineId": "L140498", "sentiment": 0.0, "text": "The man who hired me for this contract."}, {"uttered": "u4584", "characterName": "MAX", "lineId": "L140499", "sentiment": 0.0, "text": "I don't get it."}, {"uttered": "u4587", "characterName": "VINCENT", "lineId": "L140500", "sentiment": 0.0, "text": "You're gonna be me.  You're gonna go in, and you're gonna get the info on the remaining two hits."}, {"uttered": "u4584", "characterName": "MAX", "lineId": "L140501", "sentiment": 0.0, "text": "Why me?  Why don't <u>you</u> do it?"}, {"uttered": "u4587", "characterName": "VINCENT", "lineId": "L140502", "sentiment": 0.0, "text": "No client has ever seen my face, and I intend to keep it that way.  Besides, if he decides to put a bullet in my head, I don't wanna be there for it."}, {"uttered": "u4584", "characterName": "MAX", "lineId": "L140503", "sentiment": 0.0, "text": "He's gonna <u>shoot</u> me?"}, {"uttered": "u4587", "characterName": "VINCENT", "lineId": "L140504", "sentiment": 0.0, "text": "When he finds out you tossed his list? I would."}, {"uttered": "u4584", "characterName": "MAX", "lineId": "L140505", "sentiment": 0.0, "text": "No.  No way.  I can't do this."}, {"uttered": "u4587", "characterName": "VINCENT", "lineId": "L140506", "sentiment": 0.0, "text": "Max.  You threw my briefcase in the river.  You've got balls bigger than Toledo."}, {"uttered": "u4584", "characterName": "MAX", "lineId": "L140507", "sentiment": 0.0, "text": "I...I wasn't thinking.  I just did it."}, {"uttered": "u4587", "characterName": "VINCENT", "lineId": "L140508", "sentiment": 0.0, "text": "That's jazz, my friend.  You said it yourself.  So don't tell me you don't know how to play between the notes."}], "sentiment": -0.09375}, {"themes": [1, 1, 1, 0, 1, 0, 0, 0, 0, 1, 1], "dialogues": [{"uttered": "u4584", "characterName": "MAX", "lineId": "L140509", "sentiment": -0.2, "text": "Vincent.  Don't make me do this. Don't make me get people killed."}, {"uttered": "u4587", "characterName": "VINCENT", "lineId": "L140510", "sentiment": 0.0, "text": "We've both run out of options.  If it helps, take comfort in knowing you never had a choice."}], "sentiment": -0.2}, {"themes": [1, 0, 0, 0, 1, 1, 0, 1, 0, 0, 0], "dialogues": [{"uttered": "u4584", "characterName": "MAX", "lineId": "L140511", "sentiment": -0.05, "text": "How long have you been a hit man?"}, {"uttered": "u4587", "characterName": "VINCENT", "lineId": "L140512", "sentiment": 0.0, "text": "Why?"}, {"uttered": "u4584", "characterName": "MAX", "lineId": "L140513", "sentiment": 0.0, "text": "In case he asks."}, {"uttered": "u4587", "characterName": "VINCENT", "lineId": "L140514", "sentiment": 0.0, "text": "Fifteen years, although I prefer the term \"assassin.\""}, {"uttered": "u4584", "characterName": "MAX", "lineId": "L140515", "sentiment": 0.0, "text": "You get benefits?"}, {"uttered": "u4587", "characterName": "VINCENT", "lineId": "L140516", "sentiment": 0.0, "text": "No."}, {"uttered": "u4584", "characterName": "MAX", "lineId": "L140517", "sentiment": -0.714285714, "text": "Paid sick leave?"}, {"uttered": "u4587", "characterName": "VINCENT", "lineId": "L140518", "sentiment": 0.0, "text": "You tell me to start a union, I'm blowing your head off.  Quit stalling and get out of the cab."}], "sentiment": -0.382142857}, {"themes": [0, 0, 0, 0, 0, 0, 0, 0, 0, 0, 0], "dialogues": [{"uttered": "u4587", "characterName": "VINCENT", "lineId": "L140582", "sentiment": 0.633333333, "text": "Damn, Max.  I'm impressed.  Really.  I would have bet good money you wouldn't walk out of there."}, {"uttered": "u4584", "characterName": "MAX", "lineId": "L140583", "sentiment": 0.0, "text": "Makes two of us."}], "sentiment": 0.633333333}, {"themes": [0, 0, 0, 0, 1, 0, 0, 0, 0, 0, 0], "dialogues": [{"uttered": "u4587", "characterName": "VINCENT", "lineId": "L140584", "sentiment": 0.0, "text": "Washington and Holt.  Dance club called \"Fever.\" Know it?"}, {"uttered": "u4584", "characterName": "MAX", "lineId": "L140585", "sentiment": 0.1, "text": "Tribeca, near the waterfront, northeast corner.  Twelve minutes."}, {"uttered": "u4587", "characterName": "VINCENT", "lineId": "L140586", "sentiment": 0.0, "text": "You do impress me, Max.  That you do."}], "sentiment": 0.1}, {"themes": [0, 1, 0, 0, 1, 0, 0, 0, 0, 0, 1], "dialogues": [{"uttered": "u4587", "characterName": "VINCENT", "lineId": "L140605", "sentiment": 0.0, "text": "Would you have called her?"}, {"uttered": "u4584", "characterName": "MAX", "lineId": "L140606", "sentiment": 0.0, "text": "Who?"}, {"uttered": "u4587", "characterName": "VINCENT", "lineId": "L140607", "sentiment": 0.0, "text": "Your lady friend.  The one who gave you her business card.  Think she was just being polite?"}, {"uttered": "u4584", "characterName": "MAX", "lineId": "L140608", "sentiment": 0.0, "text": "I don't know."}, {"uttered": "u4587", "characterName": "VINCENT", "lineId": "L140609", "sentiment": 0.1, "text": "What holds you back, Max?  Tell me. Why does life scare you so much?"}, {"uttered": "u4584", "characterName": "MAX", "lineId": "L140610", "sentiment": 0.0, "text": "I only owe you a ride, Vincent."}, {"uttered": "u4587", "characterName": "VINCENT", "lineId": "L140611", "sentiment": 0.15, "text": "It's not what you owe <u>me.</u> Time is so fleeting.  One day it's gone.  You make it out of this alive, Max, you really should call her.  That's what I think."}], "sentiment": 0.075}, {"themes": [0, 1, 1, 0, 1, 0, 0, 0, 0, 1, 1], "dialogues": [{"uttered": "u4587", "characterName": "VINCENT", "lineId": "L140634", "sentiment": 0.35, "text": "Good.  Blood, urine and death get to you? Try deep breathing.  Or remember we all die anyway..."}, {"uttered": "u4584", "characterName": "MAX", "lineId": "L140635", "sentiment": 0.0, "text": "You had to kill Heller?!"}, {"uttered": "u4587", "characterName": "VINCENT", "lineId": "L140636", "sentiment": 0.0, "text": "Who's Heller?"}, {"uttered": "u4584", "characterName": "MAX", "lineId": "L140637", "sentiment": 0.7, "text": "That cop!  Why'd you have to do that?  You couldn't wound him?  The guy had a family, maybe, parents, kids who gotta grow up without a dad, he was probably a good guy; and he believed me..."}, {"uttered": "u4587", "characterName": "VINCENT", "lineId": "L140638", "sentiment": 0.0, "text": "I shoulda saved him 'cause he <u>believed</u> you?"}, {"uttered": "u4584", "characterName": "MAX", "lineId": "L140639", "sentiment": 0.0, "text": "No, not just that."}, {"uttered": "u4587", "characterName": "VINCENT", "lineId": "L140640", "sentiment": 0.0, "text": "Yeah, that."}, {"uttered": "u4584", "characterName": "MAX", "lineId": "L140641", "sentiment": -0.5, "text": "Yeah, so, what's wrong with that?"}, {"uttered": "u4587", "characterName": "VINCENT", "lineId": "L140642", "sentiment": 0.0, "text": "It's what I do for a living."}, {"uttered": "u4584", "characterName": "MAX", "lineId": "L140643", "sentiment": 0.0, "text": "Some living."}, {"uttered": "u4587", "characterName": "VINCENT", "lineId": "L140644", "sentiment": 0.0, "text": "Head towards Union Station."}, {"uttered": "u4584", "characterName": "MAX", "lineId": "L140645", "sentiment": 0.0, "text": "What's at Union Station?"}, {"uttered": "u4587", "characterName": "VINCENT", "lineId": "L140646", "sentiment": 0.0, "text": "How are you at math?  I was hired for five hits.  I did four."}, {"uttered": "u4584", "characterName": "MAX", "lineId": "L140647", "sentiment": 0.5, "text": "One more."}, {"uttered": "u4587", "characterName": "VINCENT", "lineId": "L140648", "sentiment": 0.0, "text": "There you go...!"}, {"uttered": "u4584", "characterName": "MAX", "lineId": "L140649", "sentiment": 0.0, "text": "Whyn't you kill me and find another cab."}, {"uttered": "u4587", "characterName": "VINCENT", "lineId": "L140650", "sentiment": -0.05, "text": "You're too good.  We're in this together.  Fates intertwined.  Cosmic coincidence and all that crap..."}, {"uttered": "u4584", "characterName": "MAX", "lineId": "L140651", "sentiment": 0.075, "text": "You're full of shit."}, {"uttered": "u4587", "characterName": "VINCENT", "lineId": "L140652", "sentiment": -0.3125, "text": "<u>I'm</u> full of shit?  You're a monument of bullshit.  You even bullshitted yourself all I am, is taking out the garbage.  Bad guys killing bad guys..."}, {"uttered": "u4584", "characterName": "MAX", "lineId": "L140653", "sentiment": 0.0, "text": "That's what you said..."}, {"uttered": "u4587", "characterName": "VINCENT", "lineId": "L140654", "sentiment": 0.0, "text": "And you believe me...?"}, {"uttered": "u4584", "characterName": "MAX", "lineId": "L140655", "sentiment": 0.0, "text": "What'd they do?"}, {"uttered": "u4587", "characterName": "VINCENT", "lineId": "L140656", "sentiment": 0.0625, "text": "How do I know?  But, they all got that \"witnesses for the prosecution\" look to me.  Probably some major federal indictment against somebody who majorly does not want to get indicted...  I dunno."}, {"uttered": "u4584", "characterName": "MAX", "lineId": "L140657", "sentiment": 0.0, "text": "That's the reason?"}, {"uttered": "u4587", "characterName": "VINCENT", "lineId": "L140658", "sentiment": 0.045454545, "text": "That's the \"why.\"  That's the why? There is no reason.  No good reason; no bad reason.  To live or to die."}, {"uttered": "u4584", "characterName": "MAX", "lineId": "L140659", "sentiment": 0.0, "text": "Then what are you?"}, {"uttered": "u4587", "characterName": "VINCENT", "lineId": "L140660", "sentiment": 0.0, "text": "...indifferent."}], "sentiment": 0.032575758}, {"themes": [0, 1, 0, 1, 0, 0, 0, 0, 1, 0, 1], "dialogues": [{"uttered": "u4587", "characterName": "VINCENT", "lineId": "L140661", "sentiment": 0.0, "text": "Get with it.  Get over it. ...millions of galaxies of hundreds of millions of stars and a speck on one in a blink...that's us.  Lost in space.  The universe doesn't care.  The cop, you, me?  Who notices?"}, {"uttered": "u4584", "characterName": "MAX", "lineId": "L140662", "sentiment": 0.0, "text": "What happened to you?"}, {"uttered": "u4587", "characterName": "VINCENT", "lineId": "L140663", "sentiment": 0.0, "text": "As in...?"}, {"uttered": "u4584", "characterName": "MAX", "lineId": "L140664", "sentiment": 0.1, "text": "Man, if someone had a gun to your head and said:  \"You gotta tell me what's goin' on with that person over there or I'll kill you\"...they'd have to kill you...  'Cause you don't have a clue for...or about...anyone...  To be like that, I don't think you, you have any of that for your own life...  Do you believe you're entitled or at least expect to draw breath in the a.m.?  Open your eyes in the morning?  I don't think you do...I don't think so...  I think you are way <u>low</u>...like in your estimation.  In your estimation of yourself.  So how'd you get that way...?"}, {"uttered": "u4587", "characterName": "VINCENT", "lineId": "L140665", "sentiment": 0.0, "text": "...all the cabbies in LA, I pull Max, the man with X-ray vision..."}, {"uttered": "u4584", "characterName": "MAX", "lineId": "L140666", "sentiment": 0.0, "text": "Answer the question."}, {"uttered": "u4587", "characterName": "VINCENT", "lineId": "L140667", "sentiment": 0.2, "text": "Look in the mirror.  ...piss-ant paper towels...a bottle of 409...saving up for goin' to the Comoros.  How much you got saved?"}, {"uttered": "u4584", "characterName": "MAX", "lineId": "L140668", "sentiment": 0.0, "text": "None of your business."}, {"uttered": "u4587", "characterName": "VINCENT", "lineId": "L140669", "sentiment": -0.02, "text": "...pie in the sky?  \"Someday my dream'll come...\"  But one night you'll wake up and realize suddenly you're old.  It hasn't happened.  It never will.  Life just flipped on you.  Tomorrow became yesterday.  Then you'll bullshit yourself it was never gonna happen, anyway, and push it back in memory...and anesthetize yourself in a Barcalounger with daytime TV for the rest of your life...  Don't talk to me about murder.  You're <u>do-in</u>' yourself...in this yellow prison with steel-belted radials. Clocking in and out everyday..."}], "sentiment": 0.044444444}, {"themes": [0, 0, 0, 0, 0, 0, 0, 0, 0, 0, 0], "dialogues": [{"uttered": "u4584", "characterName": "MAX", "lineId": "L140671", "sentiment": 0.0, "text": "'Cause I never got it straightened up; made the push, made the moves..."}, {"uttered": "u4587", "characterName": "VINCENT", "lineId": "L140672", "sentiment": -0.227777778, "text": "Slow down."}, {"uttered": "u4584", "characterName": "MAX", "lineId": "L140673", "sentiment": 0.3, "text": "I should have done that.  Fixed it and more.  Get out from under what I been under..."}], "sentiment": 0.036111111}, {"themes": [0, 0, 0, 0, 0, 0, 0, 0, 0, 0, 0], "dialogues": [{"uttered": "u4587", "characterName": "VINCENT", "lineId": "L140674", "sentiment": 0.2, "text": "You're going too fast."}, {"uttered": "u4584", "characterName": "MAX", "lineId": "L140675", "sentiment": 0.142857143, "text": "But you know what?  Nothing matters, anyway.  We are insignificant out here in the big nowhere, say the badass sociopath in my backseat.  Right? Yeah.  That's one thing I've got to thank you for, bro.  And I never saw it that way..."}], "sentiment": 0.161904762}, {"themes": [0, 0, 0, 0, 0, 0, 0, 0, 0, 0, 0], "dialogues": [{"uttered": "u4587", "characterName": "VINCENT", "lineId": "L140678", "sentiment": -0.247222222, "text": "Slow the hell down!"}, {"uttered": "u4584", "characterName": "MAX", "lineId": "L140679", "sentiment": 0.0, "text": "What are you gonna do, pull the trigger?  Kill us?  Go ahead, man! <u>Shoot</u>...my ass."}, {"uttered": "u4587", "characterName": "VINCENT", "lineId": "L140680", "sentiment": -0.247222222, "text": "Slow down!"}, {"uttered": "u4584", "characterName": "MAX", "lineId": "L140681", "sentiment": 0.0, "text": "Vincent?"}], "sentiment": -0.259375}, {"themes": [1, 0, 0, 0, 1, 0, 0, 0, 0, 0, 0], "dialogues": [{"uttered": "u4587", "characterName": "VINCENT", "lineId": "L140683", "sentiment": 0.9, "text": "Well.  That was brilliant."}, {"uttered": "u4584", "characterName": "MAX", "lineId": "L140684", "sentiment": 0.0, "text": "Was your seatbelt fastened, honey?"}], "sentiment": 0.9}, {"themes": [0, 0, 0, 0, 0, 0, 0, 0, 0, 0, 0], "dialogues": [{"uttered": "u4587", "characterName": "VINCENT", "lineId": "L140732", "sentiment": 0.0, "text": "Max?"}, {"uttered": "u4584", "characterName": "MAX", "lineId": "L140733", "sentiment": 0.0, "text": "Let her go."}], "sentiment": 0.0}], "target": "u4587"}, {"source": "u4577", "counts": 8, "lines": [{"themes": [0, 1, 0, 0, 0, 1, 0, 0, 0, 1, 0], "dialogues": [{"uttered": "u4577", "characterName": "DANIEL", "lineId": "L140319", "sentiment": 0.025, "text": "...I was just a young cat back then, about nineteen, bussin' tables in this very place.  Didn't pay but shit, but that wasn't the point.  Being around the music, that was the thing.  And I was.  Take this one night...July 22, 1964...who walks in?  Mr. Louis Armstrong."}, {"uttered": "u4587", "characterName": "VINCENT", "lineId": "L140320", "sentiment": 0.0, "text": "You're kidding me."}, {"uttered": "u4577", "characterName": "DANIEL", "lineId": "L140321", "sentiment": 0.285714286, "text": "Right through those doors.  The man himself."}, {"uttered": "u4587", "characterName": "VINCENT", "lineId": "L140322", "sentiment": 0.0, "text": "Jesus..."}, {"uttered": "u4577", "characterName": "DANIEL", "lineId": "L140323", "sentiment": -0.175, "text": "He'd come over from Queens to do the Ed Sullivan show.  After, he decides to come on up to Harlem and hang with the common folk.  That's how he was, you see.  Never forgot where he came from.  Money and fame an' all that?  Meant nothin', long as he could blow that horn.  So before you it, he's up on that stage, doin' his thing."}, {"uttered": "u4587", "characterName": "VINCENT", "lineId": "L140324", "sentiment": 0.7, "text": "Was it great?  Better than great, it had to be..."}, {"uttered": "u4577", "characterName": "DANIEL", "lineId": "L140325", "sentiment": 0.107142857, "text": "Like Winton Marsalis says, it was pure, spiritual essence.  Louis was playing.  God was smiling."}, {"uttered": "u4587", "characterName": "VINCENT", "lineId": "L140326", "sentiment": 0.136363636, "text": "You heard Armstrong play live.  I've never been this jealous.  You get to talk to him?"}, {"uttered": "u4577", "characterName": "DANIEL", "lineId": "L140327", "sentiment": 0.5, "text": "Did better'n that."}], "sentiment": 0.213311688}, {"themes": [0, 0, 0, 0, 1, 0, 0, 1, 0, 1, 0], "dialogues": [{"uttered": "u4587", "characterName": "VINCENT", "lineId": "L140328", "sentiment": 0.0, "text": "No."}, {"uttered": "u4577", "characterName": "DANIEL", "lineId": "L140329", "sentiment": 0.0, "text": "Oh, my, yes."}, {"uttered": "u4587", "characterName": "VINCENT", "lineId": "L140330", "sentiment": 0.0, "text": "Get outta here!  You and Louis?"}, {"uttered": "u4577", "characterName": "DANIEL", "lineId": "L140331", "sentiment": 0.096428571, "text": "Fella owned this place back then, Dix Dwyer, he let slip to Louis that I played.  So Pops, he just waves me right up.  My heart about stopped. But I got up there all the same, and we played for nearly twenty minutes."}, {"uttered": "u4587", "characterName": "VINCENT", "lineId": "L140332", "sentiment": -0.25, "text": "Unbelievable...  ...you hearing this?  Unbelievable."}], "sentiment": -0.019047619}, {"themes": [0, 1, 0, 0, 0, 1, 0, 1, 0, 0, 1], "dialogues": [{"uttered": "u4587", "characterName": "VINCENT", "lineId": "L140335", "sentiment": 0.0, "text": "Remember what you played?"}, {"uttered": "u4577", "characterName": "DANIEL", "lineId": "L140336", "sentiment": 0.117361111, "text": "Most vividly.  \"St. Louis Blues,\" \"Potato Head Blues,\" \"Sleepy Time Down South...\"  ...then Pops laid some \"Cornet Chop Suey\" on me, and left me in the dust like a whipped dog."}, {"uttered": "u4587", "characterName": "VINCENT", "lineId": "L140337", "sentiment": 0.0, "text": "The crowd had to dig it."}, {"uttered": "u4577", "characterName": "DANIEL", "lineId": "L140338", "sentiment": 0.396428571, "text": "The crowd was most kind.  I was born in 1945, but my life began the night of July 22, 1964.  That was the moment of my conception.  Right here in this very room."}], "sentiment": 0.256894841}, {"themes": [0, 0, 0, 0, 0, 0, 0, 0, 0, 0, 0], "dialogues": [{"uttered": "u4577", "characterName": "DANIEL", "lineId": "L140340", "sentiment": 0.0, "text": "You know Dmitri?"}, {"uttered": "u4587", "characterName": "VINCENT", "lineId": "L140341", "sentiment": 0.0, "text": "'Fraid so."}], "sentiment": 0.0}, {"themes": [0, 0, 0, 0, 0, 0, 0, 0, 0, 0, 0], "dialogues": [{"uttered": "u4577", "characterName": "DANIEL", "lineId": "L140342", "sentiment": 0.3, "text": "And here I was thinking you were such a nice guy."}, {"uttered": "u4587", "characterName": "VINCENT", "lineId": "L140343", "sentiment": 0.6, "text": "I am a nice guy, Daniel.  With a job to do.  You know how it is."}], "sentiment": 0.4}, {"themes": [1, 0, 0, 0, 1, 0, 0, 1, 0, 0, 0], "dialogues": [{"uttered": "u4577", "characterName": "DANIEL", "lineId": "L140348", "sentiment": 0.6, "text": "What kind of question?"}, {"uttered": "u4587", "characterName": "VINCENT", "lineId": "L140349", "sentiment": 0.112053571, "text": "Jazz question.  What other kind is there?  You get it right, we roll with it.  You disappear.  Tonight.  You don't go home, you don't pack a bag, you just leave town...and nobody, I mean nobody, ever hears from you or sees you again."}, {"uttered": "u4577", "characterName": "DANIEL", "lineId": "L140350", "sentiment": 0.0, "text": "How do I know you'll keep your word?"}, {"uttered": "u4587", "characterName": "VINCENT", "lineId": "L140351", "sentiment": 0.0, "text": "I never lie.  Ask Max.  Max, have I lied yet?"}], "sentiment": 0.209642857}, {"themes": [0, 0, 0, 0, 0, 0, 0, 1, 0, 1, 0], "dialogues": [{"uttered": "u4577", "characterName": "DANIEL", "lineId": "L140354", "sentiment": 0.0, "text": "One more thing.  If by some chance I get this wrong...tell Dmitri I'm sorry."}, {"uttered": "u4587", "characterName": "VINCENT", "lineId": "L140355", "sentiment": 0.0, "text": "Of course."}], "sentiment": 0.0}, {"themes": [0, 1, 0, 0, 0, 1, 1, 0, 0, 1, 0], "dialogues": [{"uttered": "u4577", "characterName": "DANIEL", "lineId": "L140356", "sentiment": 0.0, "text": "Lay it on me."}, {"uttered": "u4587", "characterName": "VINCENT", "lineId": "L140357", "sentiment": 0.083333333, "text": "It's simple.  What was your pal Louis' first musical instrument?"}, {"uttered": "u4577", "characterName": "DANIEL", "lineId": "L140358", "sentiment": 0.0, "text": "I know the answer.  I know all there is to know about Louis."}, {"uttered": "u4587", "characterName": "VINCENT", "lineId": "L140359", "sentiment": 0.0, "text": "Then let's have it."}], "sentiment": 0.083333333}], "target": "u4587"}, {"source": "u4582", "counts": 4, "lines": [{"themes": [0, 0, 0, 0, 0, 0, 0, 0, 0, 0, 0], "dialogues": [{"uttered": "u4584", "characterName": "MAX", "lineId": "L140216", "sentiment": 0.0, "text": "He'll keep calling."}, {"uttered": "u4582", "characterName": "LENNY", "lineId": "L140217", "sentiment": 0.0, "text": "Max!  Dammit!  <u>Answer!</u>"}], "sentiment": 0.0}, {"themes": [0, 0, 0, 0, 0, 0, 0, 0, 0, 0, 0], "dialogues": [{"uttered": "u4584", "characterName": "MAX", "lineId": "L140219", "sentiment": 0.0, "text": "Uh, yeah?  Lenny?  It's me."}, {"uttered": "u4582", "characterName": "LENNY", "lineId": "L140220", "sentiment": 0.0, "text": "I just got off the phone with the cops.  They called to check you brought the cab in..."}], "sentiment": 0.0}, {"themes": [0, 1, 0, 0, 1, 0, 0, 1, 0, 1, 0], "dialogues": [{"uttered": "u4584", "characterName": "MAX", "lineId": "L140221", "sentiment": 0.0, "text": "Yeah?  So?"}, {"uttered": "u4582", "characterName": "LENNY", "lineId": "L140222", "sentiment": -0.5, "text": "<u>So?</u> Aside from I hate talking to cops, they tell me you crashed the shit out of it."}, {"uttered": "u4584", "characterName": "MAX", "lineId": "L140223", "sentiment": 0.0, "text": "It got crashed!  I didn't..."}, {"uttered": "u4582", "characterName": "LENNY", "lineId": "L140224", "sentiment": -0.25, "text": "I give a shit whose fault it was, you're payin'!"}], "sentiment": -0.433333333}, {"themes": [0, 1, 0, 0, 0, 0, 0, 0, 0, 1, 1], "dialogues": [{"uttered": "u4584", "characterName": "MAX", "lineId": "L140385", "sentiment": 0.0, "text": "Yeah?"}, {"uttered": "u4582", "characterName": "LENNY", "lineId": "L140386", "sentiment": 0.0, "text": "Where you been the last two hours? Your mother's been calling every ten minutes whining about how you didn't show up."}], "sentiment": 0.0}], "target": "u4584"}, {"source": "u4582", "counts": 5, "lines": [{"themes": [0, 0, 0, 0, 0, 0, 0, 0, 0, 0, 0], "dialogues": [{"uttered": "u4582", "characterName": "LENNY", "lineId": "L140214", "sentiment": 0.0, "text": "I know you're out there!  Answer the goddamn call!"}, {"uttered": "u4587", "characterName": "VINCENT", "lineId": "L140215", "sentiment": 0.0, "text": "What happens if you don't?"}], "sentiment": 0.0}, {"themes": [0, 0, 0, 1, 0, 0, 0, 0, 0, 0, 0], "dialogues": [{"uttered": "u4587", "characterName": "VINCENT", "lineId": "L140234", "sentiment": 0.0, "text": "He's not paying you one cent!"}, {"uttered": "u4582", "characterName": "LENNY", "lineId": "L140235", "sentiment": 0.0, "text": "Who the hell is this?"}], "sentiment": 0.0}, {"themes": [0, 1, 0, 0, 0, 1, 1, 0, 0, 0, 1], "dialogues": [{"uttered": "u4587", "characterName": "VINCENT", "lineId": "L140236", "sentiment": 0.0, "text": "Vincent <u>Farrell</u>, Assistant U.S. Attorney.  A passenger in this taxicab, and I'm reporting you to the DMV..."}, {"uttered": "u4582", "characterName": "LENNY", "lineId": "L140237", "sentiment": 0.375, "text": "Let's not get excited, sir."}, {"uttered": "u4587", "characterName": "VINCENT", "lineId": "L140238", "sentiment": 0.2375, "text": "How am I supposed to not get excited, listening to you trying to extort your employee, you sarcastic prick?"}, {"uttered": "u4582", "characterName": "LENNY", "lineId": "L140239", "sentiment": 0.0, "text": "I was just tryin' to...to..."}, {"uttered": "u4587", "characterName": "VINCENT", "lineId": "L140240", "sentiment": 0.0, "text": "Tell it to Max.  Tell him he's an asshole."}], "sentiment": 0.283333333}, {"themes": [0, 1, 0, 0, 0, 0, 0, 0, 0, 1, 0], "dialogues": [{"uttered": "u4582", "characterName": "LENNY", "lineId": "L140375", "sentiment": 0.0, "text": "Max?  Maaax.  Pick up, dipshit."}, {"uttered": "u4587", "characterName": "VINCENT", "lineId": "L140376", "sentiment": 0.0, "text": "Jesus, what is with this guy?"}, {"uttered": "u4582", "characterName": "LENNY", "lineId": "L140377", "sentiment": 0.0, "text": "Maaaaaax!"}], "sentiment": 0.0}, {"themes": [0, 1, 0, 0, 0, 0, 0, 0, 0, 1, 0], "dialogues": [{"uttered": "u4587", "characterName": "VINCENT", "lineId": "L140378", "sentiment": 0.0, "text": "You hassling my driver again?"}, {"uttered": "u4582", "characterName": "LENNY", "lineId": "L140379", "sentiment": 0.0, "text": "Who is this?"}, {"uttered": "u4587", "characterName": "VINCENT", "lineId": "L140380", "sentiment": 0.0, "text": "Same fare you talked to last time. The U.S. Attorney..."}, {"uttered": "u4582", "characterName": "LENNY", "lineId": "L140381", "sentiment": 0.0, "text": "What are you guys, taking an all-night tour?"}, {"uttered": "u4587", "characterName": "VINCENT", "lineId": "L140382", "sentiment": 0.416666667, "text": "We're gay lovers, what's it to you?"}, {"uttered": "u4582", "characterName": "LENNY", "lineId": "L140383", "sentiment": -0.75, "text": "Nothin'!  Aside from Max's mother driving me crazy, I'm dancin' on a rainbow!  Get him on the line, please."}, {"uttered": "u4587", "characterName": "VINCENT", "lineId": "L140384", "sentiment": -0.1, "text": "Hang on.  Carefully..."}], "sentiment": -0.065833333}], "target": "u4587"}], "movieId": "m302", "female": [{"gender": "f", "cname": "ANNIE", "id": "u4575"}, {"gender": "f", "cname": "IDA", "id": "u4580"}], "year": "2004", "femaleLinks": [], "crossGenderLinks": [{"source": "u4584", "counts": 15, "lines": [{"themes": [0, 1, 0, 0, 0, 0, 0, 0, 0, 1, 1], "dialogues": [{"uttered": "u4584", "characterName": "MAX", "lineId": "L139970", "sentiment": 0.0, "text": "Hi ya' doin'?  Where to?"}, {"uttered": "u4575", "characterName": "ANNIE", "lineId": "L139971", "sentiment": 0.0, "text": "Park Avenue and East 2nd. Take Centre to Canal, up the Bowery, Cooper and Third, left on 41st, come around on Park."}], "sentiment": 0.0}, {"themes": [0, 0, 0, 0, 0, 0, 0, 0, 0, 1, 0], "dialogues": [{"uttered": "u4584", "characterName": "MAX", "lineId": "L139972", "sentiment": 0.0, "text": "I'll take Sixth.  It's faster."}, {"uttered": "u4575", "characterName": "ANNIE", "lineId": "L139973", "sentiment": 0.0, "text": "What?"}, {"uttered": "u4584", "characterName": "MAX", "lineId": "L139974", "sentiment": 0.0, "text": "Sixth is faster."}, {"uttered": "u4575", "characterName": "ANNIE", "lineId": "L139975", "sentiment": 0.0, "text": "Sixth is a parking lot north of 23rd this time of day."}, {"uttered": "u4584", "characterName": "MAX", "lineId": "L139976", "sentiment": 0.0, "text": "The Bowery, you gotta deal with runoff from two bridges."}, {"uttered": "u4575", "characterName": "ANNIE", "lineId": "L139977", "sentiment": 0.0, "text": "Sixth, you got delivery trucks blocking traffic at Herald Square. Look, I make this trip all the time."}, {"uttered": "u4584", "characterName": "MAX", "lineId": "L139978", "sentiment": 0.233928571, "text": "First Friday of the month?  Linens. Roll right off the trucks.  They're in and out in twenty minutes...  ...which means they left fifteen minutes ago.  Traffic will be smooth."}], "sentiment": 0.233928571}, {"themes": [0, 0, 1, 0, 0, 0, 0, 0, 0, 0, 0], "dialogues": [{"uttered": "u4584", "characterName": "MAX", "lineId": "L139979", "sentiment": 0.416666667, "text": "But Bowery's fine, if that's what you want."}, {"uttered": "u4575", "characterName": "ANNIE", "lineId": "L139980", "sentiment": -0.5, "text": "We taking bets?  What if you're wrong?"}, {"uttered": "u4584", "characterName": "MAX", "lineId": "L139981", "sentiment": 0.4, "text": "The ride is free."}, {"uttered": "u4575", "characterName": "ANNIE", "lineId": "L139982", "sentiment": 0.0, "text": "You got a deal."}], "sentiment": 0.105555556}, {"themes": [0, 1, 1, 0, 0, 0, 0, 0, 0, 1, 0], "dialogues": [{"uttered": "u4575", "characterName": "ANNIE", "lineId": "L139983", "sentiment": 0.0, "text": "Go ahead, say it."}, {"uttered": "u4584", "characterName": "MAX", "lineId": "L139984", "sentiment": 0.333333333, "text": "No.  I got lucky with the lights."}, {"uttered": "u4575", "characterName": "ANNIE", "lineId": "L139985", "sentiment": -0.107142857, "text": "No.  You were right, I was wrong...  ...Max."}], "sentiment": 0.03968254}, {"themes": [0, 1, 0, 0, 1, 1, 0, 1, 1, 1, 1], "dialogues": [{"uttered": "u4584", "characterName": "MAX", "lineId": "L139987", "sentiment": 0.0, "text": "You like Bach?"}, {"uttered": "u4575", "characterName": "ANNIE", "lineId": "L139988", "sentiment": 0.08, "text": "I used to play this piece back in high school."}, {"uttered": "u4584", "characterName": "MAX", "lineId": "L139989", "sentiment": 0.0, "text": "Let me guess.  Clarinet?"}, {"uttered": "u4575", "characterName": "ANNIE", "lineId": "L139990", "sentiment": 0.0, "text": "Violin.  I never had the lungs for wind instruments."}, {"uttered": "u4584", "characterName": "MAX", "lineId": "L139991", "sentiment": 0.0, "text": "Could'a fooled me, the way you were hollering into that cell phone."}, {"uttered": "u4575", "characterName": "ANNIE", "lineId": "L139992", "sentiment": -0.011640212, "text": "Different instrument altogether.  You know, if you'd only listened to me, we'd be bogged down in traffic right now, and you could have made yourself an extra five bucks."}, {"uttered": "u4584", "characterName": "MAX", "lineId": "L139993", "sentiment": 0.1, "text": "Keep it.  Go wild.  Have a party."}, {"uttered": "u4575", "characterName": "ANNIE", "lineId": "L139994", "sentiment": -0.1, "text": "Why'd you do that?  Don't tell me you're a gentleman, Max. I thought chivalry was dead as a necessary consequence of gender politics..."}, {"uttered": "u4584", "characterName": "MAX", "lineId": "L139995", "sentiment": 0.0, "text": "It's no big deal."}, {"uttered": "u4575", "characterName": "ANNIE", "lineId": "L139996", "sentiment": 0.5, "text": "No?  How many cabbies get you into an argument to save you money?"}, {"uttered": "u4584", "characterName": "MAX", "lineId": "L139997", "sentiment": -0.1625, "text": "There were two of us.  I had the other guy killed.  Don't need the competition..."}], "sentiment": 0.011010582}, {"themes": [0, 0, 0, 0, 0, 0, 0, 0, 0, 0, 0], "dialogues": [{"uttered": "u4575", "characterName": "ANNIE", "lineId": "L139998", "sentiment": 0.7, "text": "You're an anomaly in today's world, Max.  You're good at what you do, so you must take pride in it...?"}, {"uttered": "u4584", "characterName": "MAX", "lineId": "L139999", "sentiment": 0.0, "text": "This?  Temporary.  To pay the bills and save. I got plans..."}, {"uttered": "u4575", "characterName": "ANNIE", "lineId": "L140000", "sentiment": 0.0, "text": "Like what?"}, {"uttered": "u4584", "characterName": "MAX", "lineId": "L140001", "sentiment": 0.0, "text": "Travel...and things."}], "sentiment": 0.7}, {"themes": [0, 1, 1, 0, 0, 0, 0, 0, 0, 0, 1], "dialogues": [{"uttered": "u4584", "characterName": "MAX", "lineId": "L140002", "sentiment": 0.0, "text": "You like being a lawyer?"}, {"uttered": "u4575", "characterName": "ANNIE", "lineId": "L140003", "sentiment": 0.0, "text": "You psychic?"}, {"uttered": "u4584", "characterName": "MAX", "lineId": "L140004", "sentiment": 0.197272727, "text": "Sure.  I'm starting an 800 hotline.  Caught part of your phone call.  And even if I hadn't, there's the dark pinstripe, Armani, elegant, not too hip, which rules out advertising, plus a top-of-the-line briefcase that you live out of, looks like Bottega..."}, {"uttered": "u4575", "characterName": "ANNIE", "lineId": "L140005", "sentiment": 0.0, "text": "Bottega."}, {"uttered": "u4584", "characterName": "MAX", "lineId": "L140006", "sentiment": 0.0, "text": "...Bottega.  Guy gets in my cab wearing a catcher's mask, I think he's a ballplayer.  You?  Definitely Clarence Darrow."}], "sentiment": 0.164393939}, {"themes": [0, 1, 0, 1, 1, 0, 0, 0, 0, 0, 1], "dialogues": [{"uttered": "u4575", "characterName": "ANNIE", "lineId": "L140007", "sentiment": 0.0, "text": "Not quite.  He did defense.  I'm a prosecutor..."}, {"uttered": "u4584", "characterName": "MAX", "lineId": "L140008", "sentiment": 0.0, "text": "Big case?"}, {"uttered": "u4575", "characterName": "ANNIE", "lineId": "L140009", "sentiment": 0.0, "text": "Yeah."}], "sentiment": 0.0}, {"themes": [0, 1, 1, 0, 1, 0, 0, 1, 0, 0, 1], "dialogues": [{"uttered": "u4584", "characterName": "MAX", "lineId": "L140011", "sentiment": 0.0, "text": "You never answered my question.  You like what you do?"}, {"uttered": "u4575", "characterName": "ANNIE", "lineId": "L140012", "sentiment": 0.5, "text": "Most of the time."}, {"uttered": "u4584", "characterName": "MAX", "lineId": "L140013", "sentiment": 0.0, "text": "But not now?"}, {"uttered": "u4575", "characterName": "ANNIE", "lineId": "L140014", "sentiment": 0.475, "text": "Like you, I'm good at it.  But at this exact moment in time...like I gotta sumo wrestler on my shoulders until tomorrow morning."}, {"uttered": "u4584", "characterName": "MAX", "lineId": "L140015", "sentiment": 0.0, "text": "You need a vacation."}, {"uttered": "u4575", "characterName": "ANNIE", "lineId": "L140016", "sentiment": 0.0, "text": "Just had one."}, {"uttered": "u4584", "characterName": "MAX", "lineId": "L140017", "sentiment": -0.3125, "text": "Not in a cab...  I mean a disconnection...get your head straight...you know, get it together..."}, {"uttered": "u4575", "characterName": "ANNIE", "lineId": "L140018", "sentiment": 0.0, "text": "When was the last time you took one?"}, {"uttered": "u4584", "characterName": "MAX", "lineId": "L140019", "sentiment": -0.1875, "text": "Soon.  But I take little ones all the time.  Comoros Islands in the Indian Ocean."}, {"uttered": "u4575", "characterName": "ANNIE", "lineId": "L140020", "sentiment": 0.0, "text": "How often you go?"}, {"uttered": "u4584", "characterName": "MAX", "lineId": "L140021", "sentiment": 0.0, "text": "Dozen times a day."}], "sentiment": 0.158333333}, {"themes": [0, 1, 0, 0, 1, 0, 0, 1, 1, 0, 1], "dialogues": [{"uttered": "u4575", "characterName": "ANNIE", "lineId": "L140023", "sentiment": 0.0, "text": "No, no way, I couldn't take that..."}, {"uttered": "u4584", "characterName": "MAX", "lineId": "L140024", "sentiment": 0.5, "text": "Yes, you could.  I think you need it more than I do.  It'll help.  I promise."}], "sentiment": 0.5}, {"themes": [0, 0, 0, 0, 1, 0, 0, 0, 0, 0, 0], "dialogues": [{"uttered": "u4575", "characterName": "ANNIE", "lineId": "L140025", "sentiment": 0.15, "text": "Thanks for everything, Max.  Wow..."}, {"uttered": "u4584", "characterName": "MAX", "lineId": "L140026", "sentiment": 0.5, "text": "Sure thing."}], "sentiment": 0.266666667}, {"themes": [0, 1, 0, 0, 1, 0, 0, 0, 1, 0, 1], "dialogues": [{"uttered": "u4584", "characterName": "MAX", "lineId": "L140705", "sentiment": 0.0, "text": "Annie...it's Max."}, {"uttered": "u4575", "characterName": "ANNIE", "lineId": "L140706", "sentiment": 0.0, "text": "Max..."}, {"uttered": "u4584", "characterName": "MAX", "lineId": "L140707", "sentiment": 0.0, "text": "Max, the cab driver!"}, {"uttered": "u4575", "characterName": "ANNIE", "lineId": "L140708", "sentiment": 0.275, "text": "Max?  Oh...  ...it's kind of a strange time to be calling..."}, {"uttered": "u4584", "characterName": "MAX", "lineId": "L140709", "sentiment": 0.625, "text": "Listen to me!  Just listen, okay? There's a man, Vincent, he's coming to kill you!"}, {"uttered": "u4575", "characterName": "ANNIE", "lineId": "L140710", "sentiment": 0.0, "text": "He's...what?  Say again?  We're in cell hell..."}, {"uttered": "u4584", "characterName": "MAX", "lineId": "L140711", "sentiment": 0.0, "text": "<u>Kill</u> you!  He's coming to kill you!"}, {"uttered": "u4575", "characterName": "ANNIE", "lineId": "L140712", "sentiment": -0.125, "text": "If this is a joke, it's not funny."}, {"uttered": "u4584", "characterName": "MAX", "lineId": "L140713", "sentiment": -0.25, "text": "Dmitri hired him!  He's already killed all your witnesses, now he's coming after you!  He was stalking you when I dropped you off.  I don't know what happened, but he diverted and got into my cab, instead."}], "sentiment": 0.2215625}, {"themes": [0, 0, 0, 1, 0, 0, 0, 0, 0, 0, 0], "dialogues": [{"uttered": "u4575", "characterName": "ANNIE", "lineId": "L140714", "sentiment": 0.0, "text": "Did you say <u>Dmitri?</u> How do you know about my case?  I don't understand..."}, {"uttered": "u4584", "characterName": "MAX", "lineId": "L140715", "sentiment": 0.0, "text": "It doesn't matter!  Just get out of the goddamn building..."}], "sentiment": 0.0}, {"themes": [0, 0, 0, 0, 0, 0, 0, 0, 0, 0, 0], "dialogues": [{"uttered": "u4575", "characterName": "ANNIE", "lineId": "L140716", "sentiment": 0.0, "text": "...okay, Max, I believe you...I'll get out of the building..."}, {"uttered": "u4584", "characterName": "MAX", "lineId": "L140717", "sentiment": 0.0, "text": "No, no, <u>wait</u>..."}], "sentiment": 0.0}, {"themes": [0, 1, 0, 1, 0, 0, 0, 0, 1, 0, 1], "dialogues": [{"uttered": "u4584", "characterName": "MAX", "lineId": "L140718", "sentiment": 0.0, "text": "...he's two floors below you."}, {"uttered": "u4575", "characterName": "ANNIE", "lineId": "L140719", "sentiment": 0.0, "text": "In my office?"}, {"uttered": "u4584", "characterName": "MAX", "lineId": "L140720", "sentiment": 0.0, "text": "Where are you, what floor?"}, {"uttered": "u4575", "characterName": "ANNIE", "lineId": "L140721", "sentiment": 0.0, "text": "Seventh, files section.  What should I do?"}, {"uttered": "u4584", "characterName": "MAX", "lineId": "L140722", "sentiment": 0.446428571, "text": "He doesn't know you're up there!  Just stay right where you are!  Call the police!"}, {"uttered": "u4575", "characterName": "ANNIE", "lineId": "L140723", "sentiment": 0.5, "text": "Max, I'm scared.  Are you sure?"}, {"uttered": "u4584", "characterName": "MAX", "lineId": "L140724", "sentiment": 0.0, "text": "Yes!  Stay put, goddamn it!  Don't move from that spot..."}], "sentiment": 0.613839286}], "target": "u4575"}, {"source": "u4584", "counts": 4, "lines": [{"themes": [0, 0, 0, 1, 1, 1, 1, 0, 0, 0, 0], "dialogues": [{"uttered": "u4584", "characterName": "MAX", "lineId": "L140405", "sentiment": 0.0, "text": "Hi, Ma."}, {"uttered": "u4580", "characterName": "IDA", "lineId": "L140406", "sentiment": 0.0, "text": "I've been calling and calling."}, {"uttered": "u4584", "characterName": "MAX", "lineId": "L140407", "sentiment": 0.0, "text": "I got caught up at work."}, {"uttered": "u4580", "characterName": "IDA", "lineId": "L140408", "sentiment": -1.0, "text": "You couldn't pick up a phone?  I'm lying here, wondering if something horrible happened..."}, {"uttered": "u4584", "characterName": "MAX", "lineId": "L140409", "sentiment": 0.0, "text": "I brought you flowers."}, {"uttered": "u4580", "characterName": "IDA", "lineId": "L140410", "sentiment": 0.0, "text": "What am I gonna do with flowers?"}, {"uttered": "u4584", "characterName": "MAX", "lineId": "L140411", "sentiment": 0.0, "text": "You're gonna cheer up."}, {"uttered": "u4580", "characterName": "IDA", "lineId": "L140412", "sentiment": 0.0, "text": "By worrying about you spending money on foolish things?  So I can watch them wilt?"}, {"uttered": "u4584", "characterName": "MAX", "lineId": "L140413", "sentiment": 0.0, "text": "He paid for 'em."}], "sentiment": -1.0}, {"themes": [0, 0, 0, 0, 0, 0, 0, 0, 0, 0, 0], "dialogues": [{"uttered": "u4580", "characterName": "IDA", "lineId": "L140416", "sentiment": 0.85, "text": "You paid for my flowers?  They're beautiful.  Max, you gonna introduce us?"}, {"uttered": "u4584", "characterName": "MAX", "lineId": "L140417", "sentiment": 0.0, "text": "Mom, Vincent.  Vincent, my mother, Ida Rilke."}], "sentiment": 0.85}, {"themes": [0, 1, 0, 1, 0, 0, 0, 0, 0, 0, 1], "dialogues": [{"uttered": "u4584", "characterName": "MAX", "lineId": "L140428", "sentiment": 0.0, "text": "I'm...in...the...room, here.  Don't talk about me like I'm not in the room."}, {"uttered": "u4580", "characterName": "IDA", "lineId": "L140429", "sentiment": 0.0, "text": "What's he sayin'?"}, {"uttered": "u4584", "characterName": "MAX", "lineId": "L140430", "sentiment": 0.285714286, "text": "I'm standing right here."}, {"uttered": "u4580", "characterName": "IDA", "lineId": "L140431", "sentiment": 0.333333333, "text": "Yesss, you are.  He's artistic."}], "sentiment": 0.30952381}, {"themes": [0, 0, 0, 0, 1, 0, 0, 0, 0, 0, 0], "dialogues": [{"uttered": "u4584", "characterName": "MAX", "lineId": "L140440", "sentiment": 0.416666667, "text": "I came to see you, you look fine.  We gotta go."}, {"uttered": "u4580", "characterName": "IDA", "lineId": "L140441", "sentiment": 0.6, "text": "Vincent.  It was nice to meet you. Visit again?"}], "sentiment": 0.508333333}], "target": "u4580"}, {"source": "u4587", "counts": 7, "lines": [{"themes": [0, 1, 0, 0, 0, 0, 0, 0, 0, 0, 1], "dialogues": [{"uttered": "u4580", "characterName": "IDA", "lineId": "L140414", "sentiment": 0.0, "text": "Why didn't you tell me we had company?  And what's your name?"}, {"uttered": "u4587", "characterName": "VINCENT", "lineId": "L140415", "sentiment": 0.0, "text": "No harm done, ma'am."}], "sentiment": 0.0}, {"themes": [0, 1, 0, 0, 0, 0, 0, 0, 0, 0, 1], "dialogues": [{"uttered": "u4587", "characterName": "VINCENT", "lineId": "L140418", "sentiment": 0.8, "text": "Happy to meet you, Mrs. Rilke."}, {"uttered": "u4580", "characterName": "IDA", "lineId": "L140419", "sentiment": 0.0, "text": "Oh, call me Ida.  To what do we owe the pleasure?"}], "sentiment": 0.8}, {"themes": [0, 0, 0, 0, 0, 0, 0, 0, 0, 0, 0], "dialogues": [{"uttered": "u4587", "characterName": "VINCENT", "lineId": "L140420", "sentiment": 0.0, "text": "I was with Max when he got the call."}, {"uttered": "u4580", "characterName": "IDA", "lineId": "L140421", "sentiment": -0.155555556, "text": "And you came all the way down here to see me?"}, {"uttered": "u4587", "characterName": "VINCENT", "lineId": "L140422", "sentiment": 0.0, "text": "It's nothing."}, {"uttered": "u4580", "characterName": "IDA", "lineId": "L140423", "sentiment": 0.0, "text": "Tell my son.  You have to hold a gun to his head to get him to come see me."}, {"uttered": "u4587", "characterName": "VINCENT", "lineId": "L140424", "sentiment": 0.0, "text": "Tell me about it."}], "sentiment": -0.155555556}, {"themes": [1, 1, 0, 0, 1, 0, 0, 0, 0, 1, 0], "dialogues": [{"uttered": "u4587", "characterName": "VINCENT", "lineId": "L140426", "sentiment": 0.5, "text": "Client?  I like to think of myself as more of a friend.  A mentor."}, {"uttered": "u4580", "characterName": "IDA", "lineId": "L140427", "sentiment": 0.1, "text": "Max never had many friends.  So much with the piano.  Always keeping to himself, it's unhealthy..."}], "sentiment": 0.2}, {"themes": [0, 0, 0, 0, 0, 0, 0, 0, 0, 0, 0], "dialogues": [{"uttered": "u4587", "characterName": "VINCENT", "lineId": "L140432", "sentiment": 0.75, "text": "I'm sure you're very proud of Max."}, {"uttered": "u4580", "characterName": "IDA", "lineId": "L140433", "sentiment": 0.8, "text": "Of course I'm proud.  You know he started with nothing?  Look at him today.  Playing concerts."}], "sentiment": 0.766666667}, {"themes": [0, 1, 1, 0, 1, 1, 0, 0, 0, 1, 0], "dialogues": [{"uttered": "u4587", "characterName": "VINCENT", "lineId": "L140437", "sentiment": 0.0, "text": "Quite an achievement..."}, {"uttered": "u4580", "characterName": "IDA", "lineId": "L140438", "sentiment": 0.0, "text": "What's your name?"}, {"uttered": "u4587", "characterName": "VINCENT", "lineId": "L140439", "sentiment": 0.0, "text": "Vincent..."}], "sentiment": 0.0}, {"themes": [0, 1, 0, 0, 0, 1, 1, 1, 1, 1, 0], "dialogues": [{"uttered": "u4587", "characterName": "VINCENT", "lineId": "L140442", "sentiment": 0.0, "text": "I'm in town for a short time."}, {"uttered": "u4580", "characterName": "IDA", "lineId": "L140443", "sentiment": 0.0, "text": "Try?"}, {"uttered": "u4587", "characterName": "VINCENT", "lineId": "L140444", "sentiment": 0.0, "text": "Of course!"}], "sentiment": 0.0}], "target": "u4580"}], "male": [{"gender": "m", "cname": "DANIEL", "id": "u4577"}, {"gender": "m", "cname": "DMITRI", "id": "u4578"}, {"gender": "m", "cname": "LENNY", "id": "u4582"}, {"gender": "m", "cname": "MAX", "id": "u4584"}, {"gender": "m", "cname": "VINCENT", "id": "u4587"}], "movieTitle": "collateral"}