{"rating": "6.6", "maleLinks": [{"source": "u5878", "counts": 5, "lines": [{"themes": [0, 0, 0, 0, 0, 1, 1, 0, 0, 0, 0], "dialogues": [{"uttered": "u5891", "characterName": "TALLEY", "lineId": "L287527", "sentiment": 0.0, "text": "I need to work out some stuff."}, {"uttered": "u5878", "characterName": "JANE", "lineId": "L287528", "sentiment": 0.0, "text": "You're hiding, Jeffrey.  You're hiding from the job and you're hiding from me."}, {"uttered": "u5891", "characterName": "TALLEY", "lineId": "L287529", "sentiment": 0.0, "text": "I still see that boy's eyes."}], "sentiment": 0.0}, {"themes": [0, 0, 0, 0, 1, 1, 1, 0, 0, 0, 0], "dialogues": [{"uttered": "u5891", "characterName": "TALLEY", "lineId": "L287536", "sentiment": 0.5, "text": "Can we talk some more when you get here?"}, {"uttered": "u5878", "characterName": "JANE", "lineId": "L287537", "sentiment": 0.0, "text": "We'll see you in a couple of hours."}], "sentiment": 0.5}, {"themes": [0, 0, 0, 0, 0, 0, 0, 0, 0, 0, 0], "dialogues": [{"uttered": "u5891", "characterName": "TALLEY", "lineId": "L287688", "sentiment": 0.242857143, "text": "I should've called.  This thing broke right after we spoke, then everything happened so fast --"}, {"uttered": "u5878", "characterName": "JANE", "lineId": "L287689", "sentiment": 0.0, "text": "Don't worry about it.  How are you doing?"}, {"uttered": "u5891", "characterName": "TALLEY", "lineId": "L287690", "sentiment": 0.0, "text": "The Sheriffs will take over when they get here."}, {"uttered": "u5878", "characterName": "JANE", "lineId": "L287691", "sentiment": 0.0, "text": "But they're not here yet.  Tell me about <u>you</u>."}], "sentiment": 0.242857143}, {"themes": [0, 1, 0, 0, 0, 0, 1, 0, 0, 1, 0], "dialogues": [{"uttered": "u5891", "characterName": "TALLEY", "lineId": "L287693", "sentiment": 0.0, "text": "Why don't you guys grab some dinner at the Thai place?  I'll meet you there as soon as I can."}, {"uttered": "u5878", "characterName": "JANE", "lineId": "L287694", "sentiment": 0.5, "text": "You sure?"}, {"uttered": "u5891", "characterName": "TALLEY", "lineId": "L287695", "sentiment": -0.05, "text": "I don't know how long I'll be stuck here."}, {"uttered": "u5878", "characterName": "JANE", "lineId": "L287696", "sentiment": 0.0, "text": "I'm in no rush.  Maybe later we can talk."}], "sentiment": 0.15}, {"themes": [0, 0, 0, 0, 0, 0, 0, 0, 0, 0, 0], "dialogues": [{"uttered": "u5891", "characterName": "TALLEY", "lineId": "L287698", "sentiment": 0.0, "text": "I'm scared shitless."}, {"uttered": "u5878", "characterName": "JANE", "lineId": "L287699", "sentiment": 0.5, "text": "That's okay.  I love you anyway."}], "sentiment": 0.5}], "target": "u5891"}, {"source": "u5882", "counts": 5, "lines": [{"themes": [0, 0, 0, 0, 1, 1, 0, 0, 0, 0, 0], "dialogues": [{"uttered": "u5891", "characterName": "TALLEY", "lineId": "L288031", "sentiment": 0.0, "text": "I'm the chief of police here.  I have to talk to him."}, {"uttered": "u5882", "characterName": "KLAUS", "lineId": "L288032", "sentiment": 0.0, "text": "Ain't gonna happen.  We've got unequal pupilation.  He could have an intracranial hematoma or a fracture or both."}], "sentiment": 0.0}, {"themes": [0, 0, 0, 0, 1, 1, 1, 0, 0, 0, 0], "dialogues": [{"uttered": "u5891", "characterName": "TALLEY", "lineId": "L288033", "sentiment": 0.0, "text": "Smith!  Wake up!"}, {"uttered": "u5882", "characterName": "KLAUS", "lineId": "L288034", "sentiment": 0.0, "text": "What are you doing?!  Stop that!"}], "sentiment": 0.0}, {"themes": [0, 0, 0, 0, 1, 1, 1, 0, 0, 0, 0], "dialogues": [{"uttered": "u5882", "characterName": "KLAUS", "lineId": "L288039", "sentiment": 0.0, "text": "I'm not going to wake him.  I don't even know that I can."}, {"uttered": "u5891", "characterName": "TALLEY", "lineId": "L288040", "sentiment": 0.0, "text": "Just one question.  Please."}, {"uttered": "u5882", "characterName": "KLAUS", "lineId": "L288041", "sentiment": 0.0, "text": "He.  Can't.  Answer."}], "sentiment": 0.0}, {"themes": [0, 0, 0, 0, 0, 0, 0, 0, 0, 0, 0], "dialogues": [{"uttered": "u5891", "characterName": "TALLEY", "lineId": "L288149", "sentiment": 0.3, "text": "I'm Jeff Talley, the Bristo chief of police.  So far as we know, your children are okay."}, {"uttered": "u5882", "characterName": "KLAUS", "lineId": "L288150", "sentiment": 0.0, "text": "Chief Talley is the one who got you out."}, {"uttered": "u5891", "characterName": "TALLEY", "lineId": "L288151", "sentiment": 0.0, "text": "I need to talk to him.  Alone."}], "sentiment": 0.3}, {"themes": [0, 0, 0, 0, 1, 0, 0, 1, 0, 0, 0], "dialogues": [{"uttered": "u5882", "characterName": "KLAUS", "lineId": "L288155", "sentiment": 0.0, "text": "That's enough."}, {"uttered": "u5891", "characterName": "TALLEY", "lineId": "L288156", "sentiment": 0.0, "text": "Another minute.  Please --"}], "sentiment": 0.0}], "target": "u5891"}, {"source": "u5891", "counts": 11, "lines": [{"themes": [0, 0, 0, 0, 0, 0, 0, 1, 0, 0, 0], "dialogues": [{"uttered": "u5891", "characterName": "TALLEY", "lineId": "L287919", "sentiment": 0.0, "text": "This is Chief Talley.  Tell me your name, son."}, {"uttered": "u5894", "characterName": "THOMAS", "lineId": "L287920", "sentiment": 0.0, "text": "Thomas Smith.  I'm in the house that's on TV.  Dennis hit my dad and now he won't wake up.  You gotta help him."}], "sentiment": 0.0}, {"themes": [0, 0, 0, 0, 0, 1, 0, 1, 1, 0, 0], "dialogues": [{"uttered": "u5891", "characterName": "TALLEY", "lineId": "L287921", "sentiment": -0.007407407, "text": "Slow down, Thomas.  Take it easy and talk to me.  Was your father shot?"}, {"uttered": "u5894", "characterName": "THOMAS", "lineId": "L287922", "sentiment": 0.1, "text": "Dennis hit him.  His head's all big and he won't wake up.  I'm really scared."}, {"uttered": "u5891", "characterName": "TALLEY", "lineId": "L287923", "sentiment": 0.0, "text": "How about you and your sister?"}, {"uttered": "u5894", "characterName": "THOMAS", "lineId": "L287924", "sentiment": 0.5, "text": "We're okay."}, {"uttered": "u5891", "characterName": "TALLEY", "lineId": "L287925", "sentiment": 0.285714286, "text": "Where are you right now?"}, {"uttered": "u5894", "characterName": "THOMAS", "lineId": "L287926", "sentiment": 0.0, "text": "In my room."}], "sentiment": 0.137641723}, {"themes": [0, 1, 0, 0, 0, 0, 0, 1, 0, 1, 0], "dialogues": [{"uttered": "u5891", "characterName": "TALLEY", "lineId": "L287927", "sentiment": 0.0, "text": "That's on the second floor.  Could you climb out your window if we were downstairs to catch you?"}, {"uttered": "u5894", "characterName": "THOMAS", "lineId": "L287928", "sentiment": 0.0, "text": "They nailed the windows.  I can't get'm open."}], "sentiment": 0.0}, {"themes": [0, 0, 0, 0, 0, 0, 0, 0, 0, 0, 0], "dialogues": [{"uttered": "u5891", "characterName": "TALLEY", "lineId": "L287929", "sentiment": 0.0, "text": "I've got the boy on the phone.  He's using a cell phone.  What was that, son?  I didn't hear you."}, {"uttered": "u5894", "characterName": "THOMAS", "lineId": "L287930", "sentiment": 0.0, "text": "If I try to climb out they'll see me on the security cameras.  They would see you outside, too --"}], "sentiment": 0.0}, {"themes": [0, 0, 1, 0, 1, 0, 0, 0, 0, 0, 0], "dialogues": [{"uttered": "u5894", "characterName": "THOMAS", "lineId": "L288062", "sentiment": 0.5, "text": "Is my daddy okay?"}, {"uttered": "u5891", "characterName": "TALLEY", "lineId": "L288063", "sentiment": 0.392857143, "text": "The doctors are taking care of him right now.  Thomas . . . are you safe?  Can you talk?"}, {"uttered": "u5894", "characterName": "THOMAS", "lineId": "L288064", "sentiment": 0.0, "text": "I think so."}, {"uttered": "u5891", "characterName": "TALLEY", "lineId": "L288065", "sentiment": 0.5, "text": "I need your help with something.  But if you think those guys could catch you, then I don't want you to do it, okay?"}, {"uttered": "u5894", "characterName": "THOMAS", "lineId": "L288066", "sentiment": 0.5, "text": "Okay."}, {"uttered": "u5891", "characterName": "TALLEY", "lineId": "L288067", "sentiment": -0.333333333, "text": "I'm serious, Thomas; I don't want you to get hurt."}, {"uttered": "u5894", "characterName": "THOMAS", "lineId": "L288068", "sentiment": 0.0, "text": "What do you want me to do?"}, {"uttered": "u5891", "characterName": "TALLEY", "lineId": "L288069", "sentiment": 0.25, "text": "Your dad has two computer disks.  They have funny names:  Marlon and Al."}, {"uttered": "u5894", "characterName": "THOMAS", "lineId": "L288070", "sentiment": 0.0, "text": "He has lots of disks."}, {"uttered": "u5891", "characterName": "TALLEY", "lineId": "L288071", "sentiment": 0.0, "text": "I think he was working on them today, so they're probably in his office.  Could you find them and see who they belong to?"}, {"uttered": "u5894", "characterName": "THOMAS", "lineId": "L288072", "sentiment": 0.0, "text": "Dennis won't let me go to the desk.  He makes me sit on the floor."}], "sentiment": 0.31462585}, {"themes": [0, 0, 0, 0, 0, 0, 0, 0, 0, 0, 0], "dialogues": [{"uttered": "u5894", "characterName": "THOMAS", "lineId": "L288073", "sentiment": 0.25, "text": "But I might be able to sneak into the office if they're not around.  Then I could open the disks here in my room."}, {"uttered": "u5891", "characterName": "TALLEY", "lineId": "L288074", "sentiment": 0.0, "text": "I thought they locked you in your room."}, {"uttered": "u5894", "characterName": "THOMAS", "lineId": "L288075", "sentiment": 0.0, "text": "I can get into the crawlspace from my closet and climb all over the house."}, {"uttered": "u5891", "characterName": "TALLEY", "lineId": "L288076", "sentiment": 0.0, "text": "Can you get into the office?"}, {"uttered": "u5894", "characterName": "THOMAS", "lineId": "L288077", "sentiment": 0.285714286, "text": "I can get into the den.  The office is right across the hall."}], "sentiment": 0.261904762}, {"themes": [0, 0, 0, 0, 0, 0, 0, 0, 0, 0, 0], "dialogues": [{"uttered": "u5891", "characterName": "TALLEY", "lineId": "L288078", "sentiment": 0.0, "text": "If I get Rooney into the back of the house, can you find the disks without being caught?"}, {"uttered": "u5894", "characterName": "THOMAS", "lineId": "L288079", "sentiment": 0.0, "text": "Yes, sir."}], "sentiment": 0.0}, {"themes": [1, 1, 0, 0, 1, 0, 0, 1, 0, 1, 0], "dialogues": [{"uttered": "u5891", "characterName": "TALLEY", "lineId": "L288125", "sentiment": 0.0, "text": "Can you open them?"}, {"uttered": "u5894", "characterName": "THOMAS", "lineId": "L288126", "sentiment": 0.0, "text": "I opened Marlon.  I think it's somebody's taxes."}, {"uttered": "u5891", "characterName": "TALLEY", "lineId": "L288127", "sentiment": 0.0, "text": "Look for names.  Does it say whose taxes they are?"}], "sentiment": 0.0}, {"themes": [0, 0, 0, 0, 1, 1, 0, 0, 0, 0, 0], "dialogues": [{"uttered": "u5894", "characterName": "THOMAS", "lineId": "L288128", "sentiment": 0.0, "text": "I don't see any people names.  It's all businesses."}, {"uttered": "u5891", "characterName": "TALLEY", "lineId": "L288129", "sentiment": 0.0, "text": "Try Al.  See if you can open Al."}], "sentiment": 0.0}, {"themes": [1, 0, 0, 0, 1, 1, 0, 0, 0, 0, 0], "dialogues": [{"uttered": "u5894", "characterName": "THOMAS", "lineId": "L288130", "sentiment": 0.0, "text": "Yeah!  Here's a name.  This is somebody's personal tax --"}, {"uttered": "u5891", "characterName": "TALLEY", "lineId": "L288131", "sentiment": 0.0, "text": "Who is it?"}, {"uttered": "u5894", "characterName": "THOMAS", "lineId": "L288132", "sentiment": 0.0, "text": "Charles G. Benza.  They're coming!"}], "sentiment": 0.0}, {"themes": [0, 0, 0, 0, 0, 0, 0, 0, 0, 0, 0], "dialogues": [{"uttered": "u5891", "characterName": "TALLEY", "lineId": "L288298", "sentiment": 0.0, "text": "Are the disks still in your room?"}, {"uttered": "u5894", "characterName": "THOMAS", "lineId": "L288299", "sentiment": 0.285714286, "text": "No!  They're right here --"}], "sentiment": 0.285714286}], "target": "u5894"}, {"source": "u5869", "counts": 4, "lines": [{"themes": [0, 0, 0, 0, 0, 0, 0, 0, 0, 0, 0], "dialogues": [{"uttered": "u5891", "characterName": "TALLEY", "lineId": "L287551", "sentiment": 0.0, "text": "Mike!  Mike, can you hear me?"}, {"uttered": "u5869", "characterName": "ANDERS", "lineId": "L287552", "sentiment": -0.25, "text": "I think he's dead!"}, {"uttered": "u5891", "characterName": "TALLEY", "lineId": "L287553", "sentiment": 0.0, "text": "Don't shout, Larry.  I'm three feet away."}], "sentiment": -0.25}, {"themes": [0, 1, 1, 0, 0, 0, 0, 0, 0, 1, 0], "dialogues": [{"uttered": "u5869", "characterName": "ANDERS", "lineId": "L287607", "sentiment": 0.0, "text": "The house belongs to Walter and Pamela Smith.  They've got two kids, a girl about fifteen and a boy younger, Jennifer and Thomas."}, {"uttered": "u5891", "characterName": "TALLEY", "lineId": "L287608", "sentiment": 0.0, "text": "That would be the girl who opened the door.  Are the others inside?"}, {"uttered": "u5869", "characterName": "ANDERS", "lineId": "L287609", "sentiment": 0.0, "text": "The mother is in Florida visiting her sister.  The father works at home, so he's probably inside."}], "sentiment": 0.0}, {"themes": [0, 0, 0, 0, 0, 0, 0, 0, 0, 0, 0], "dialogues": [{"uttered": "u5891", "characterName": "TALLEY", "lineId": "L287768", "sentiment": 0.0, "text": "Call the Palmdale City Attorney for a telephonic search warrant.  When you get the warrant, have Mikkelson and Dreyer search his house."}, {"uttered": "u5869", "characterName": "ANDERS", "lineId": "L287769", "sentiment": 0.0, "text": "Yes, sir."}], "sentiment": 0.0}, {"themes": [0, 0, 0, 0, 1, 0, 0, 1, 0, 0, 0], "dialogues": [{"uttered": "u5869", "characterName": "ANDERS", "lineId": "L287977", "sentiment": 0.295238095, "text": "Wow.  Sure, right away, Chief."}, {"uttered": "u5891", "characterName": "TALLEY", "lineId": "L287978", "sentiment": -0.125, "text": "Don't tell anyone what you're doing, not Louise, not the other guys, not the Sheriffs.  You understand me, Larry?"}, {"uttered": "u5869", "characterName": "ANDERS", "lineId": "L287979", "sentiment": 0.0, "text": "I guess so."}, {"uttered": "u5891", "characterName": "TALLEY", "lineId": "L287980", "sentiment": -0.4, "text": "Fuck guessing.  You keep your mouth shut."}, {"uttered": "u5869", "characterName": "ANDERS", "lineId": "L287981", "sentiment": 0.2, "text": "I will, Chief.  Absolutely."}, {"uttered": "u5891", "characterName": "TALLEY", "lineId": "L287982", "sentiment": 0.0, "text": "Get to work."}], "sentiment": 0.093452381}], "target": "u5891"}, {"source": "u5874", "counts": 17, "lines": [{"themes": [0, 0, 0, 0, 0, 0, 0, 0, 0, 0, 0], "dialogues": [{"uttered": "u5881", "characterName": "KEVIN", "lineId": "L287459", "sentiment": -0.8, "text": "C'mon, Dennis, this is stupid.  I thought we were gonna go to the movies."}, {"uttered": "u5874", "characterName": "DENNIS", "lineId": "L287460", "sentiment": 0.642857143, "text": "Mars?!  Whattaya think, dude?  Out here on the edge, no one around, it's perfect, right?"}], "sentiment": 0.095238095}, {"themes": [0, 0, 0, 0, 1, 0, 1, 0, 0, 0, 0], "dialogues": [{"uttered": "u5874", "characterName": "DENNIS", "lineId": "L287462", "sentiment": 0.425, "text": "Try to act cool, okay?  He's gonna think you're a dick."}, {"uttered": "u5881", "characterName": "KEVIN", "lineId": "L287463", "sentiment": 0.0, "text": "Robbing this place is gonna put you back in prison."}, {"uttered": "u5874", "characterName": "DENNIS", "lineId": "L287464", "sentiment": 0.0, "text": "Not if they don't catch us, Kevin."}, {"uttered": "u5881", "characterName": "KEVIN", "lineId": "L287465", "sentiment": 0.0, "text": "We got jobs, man; we're working.  Why even take the chance?"}, {"uttered": "u5874", "characterName": "DENNIS", "lineId": "L287466", "sentiment": -0.2, "text": "Because if you don't take the chance, you're already dead."}], "sentiment": 0.1625}, {"themes": [0, 0, 0, 0, 0, 0, 0, 0, 0, 0, 0], "dialogues": [{"uttered": "u5881", "characterName": "KEVIN", "lineId": "L287473", "sentiment": 0.0, "text": "There's fuckin' blood all over you!"}, {"uttered": "u5874", "characterName": "DENNIS", "lineId": "L287474", "sentiment": 0.0, "text": "I didn't know he would have a gun!  It just went off!"}], "sentiment": 0.0}, {"themes": [0, 0, 0, 0, 0, 0, 0, 0, 0, 0, 0], "dialogues": [{"uttered": "u5881", "characterName": "KEVIN", "lineId": "L287479", "sentiment": 0.0, "text": "That woman's gonna call the cops."}, {"uttered": "u5874", "characterName": "DENNIS", "lineId": "L287480", "sentiment": 0.052777778, "text": "Shut up, goddamnit!  Just calm down!"}, {"uttered": "u5881", "characterName": "KEVIN", "lineId": "L287481", "sentiment": -0.2, "text": "What if he's dead?  What if you killed him?"}], "sentiment": -0.073611111}, {"themes": [0, 0, 0, 0, 1, 0, 0, 0, 0, 0, 0], "dialogues": [{"uttered": "u5874", "characterName": "DENNIS", "lineId": "L287483", "sentiment": 0.0, "text": "That's why we gotta keep going.  I'm not gonna go in for murder."}, {"uttered": "u5881", "characterName": "KEVIN", "lineId": "L287484", "sentiment": 0.0, "text": "We're on foot.  We can't get away."}, {"uttered": "u5874", "characterName": "DENNIS", "lineId": "L287485", "sentiment": 0.0, "text": "We're surrounded by houses, dumbass. Every house has a car in the garage. All we have to do is take one."}], "sentiment": 0.0}, {"themes": [0, 0, 1, 0, 0, 0, 0, 0, 0, 0, 0], "dialogues": [{"uttered": "u5881", "characterName": "KEVIN", "lineId": "L287581", "sentiment": 0.0, "text": "We could've gone out the back!  You didn't have to shoot!"}, {"uttered": "u5874", "characterName": "DENNIS", "lineId": "L287582", "sentiment": -0.5, "text": "Stop it!  They found the truck, Kev! They're already behind us!"}, {"uttered": "u5881", "characterName": "KEVIN", "lineId": "L287583", "sentiment": -0.4, "text": "We should give up.  All we're doing is making it worse."}], "sentiment": -0.3}, {"themes": [0, 0, 0, 0, 0, 0, 0, 0, 0, 0, 0], "dialogues": [{"uttered": "u5881", "characterName": "KEVIN", "lineId": "L287657", "sentiment": 0.0, "text": "I have to tell you something --"}, {"uttered": "u5874", "characterName": "DENNIS", "lineId": "L287658", "sentiment": 0.0, "text": "We gotta find a way outta here is what we gotta do!"}, {"uttered": "u5881", "characterName": "KEVIN", "lineId": "L287659", "sentiment": 0.0, "text": "It's about Mars --"}], "sentiment": 0.0}, {"themes": [0, 0, 0, 0, 0, 0, 1, 0, 0, 0, 0], "dialogues": [{"uttered": "u5881", "characterName": "KEVIN", "lineId": "L287660", "sentiment": 0.0, "text": "That cop didn't pull his gun.  Mars lied. He just started shooting!"}, {"uttered": "u5874", "characterName": "DENNIS", "lineId": "L287661", "sentiment": 0.0, "text": "Bullshit.  Why would Mars do that?"}, {"uttered": "u5881", "characterName": "KEVIN", "lineId": "L287662", "sentiment": 0.0, "text": "I was <u>there</u>, Dennis!  I <u>saw</u>!  It's like he <u>wanted</u> to shoot that cop."}, {"uttered": "u5874", "characterName": "DENNIS", "lineId": "L287663", "sentiment": -0.8, "text": "You're being stupid.  Check out the bathroom.  Maybe we can sneak out a window --"}], "sentiment": -0.8}, {"themes": [0, 0, 0, 0, 0, 0, 0, 0, 0, 0, 0], "dialogues": [{"uttered": "u5881", "characterName": "KEVIN", "lineId": "L287665", "sentiment": 0.0, "text": "Jesus.  What is this?"}, {"uttered": "u5874", "characterName": "DENNIS", "lineId": "L287666", "sentiment": -0.8, "text": "Are you totally stupid?  What does it look like?"}], "sentiment": -0.8}, {"themes": [0, 0, 0, 0, 0, 0, 0, 0, 0, 0, 0], "dialogues": [{"uttered": "u5881", "characterName": "KEVIN", "lineId": "L287785", "sentiment": 0.5, "text": "Everyone knows what we look like, Dennis. We won't be able to hide."}, {"uttered": "u5874", "characterName": "DENNIS", "lineId": "L287786", "sentiment": 0.25, "text": "Jesus, first Mars, now you.  You two need anti-depressants."}], "sentiment": 0.375}, {"themes": [0, 0, 0, 0, 0, 0, 0, 0, 0, 0, 0], "dialogues": [{"uttered": "u5881", "characterName": "KEVIN", "lineId": "L287848", "sentiment": 0.0, "text": "Someone should stay with Mr. Smith.  What if he wakes up?"}, {"uttered": "u5874", "characterName": "DENNIS", "lineId": "L287849", "sentiment": 0.0, "text": "That's why we tied him, dumbass.  Now come here and see this --"}], "sentiment": 0.0}, {"themes": [0, 0, 0, 0, 1, 0, 0, 0, 0, 0, 0], "dialogues": [{"uttered": "u5874", "characterName": "DENNIS", "lineId": "L287850", "sentiment": 0.5, "text": "These bushes follow the wall into the neighbor's yard.  All we need is some kind of diversion and we're home free."}, {"uttered": "u5881", "characterName": "KEVIN", "lineId": "L287851", "sentiment": -0.6, "text": "That's crazy, Dennis.  The cops will see us."}, {"uttered": "u5874", "characterName": "DENNIS", "lineId": "L287852", "sentiment": 0.0, "text": "Not if they're looking at something else."}, {"uttered": "u5881", "characterName": "KEVIN", "lineId": "L287853", "sentiment": 0.0, "text": "Like what?"}], "sentiment": 0.133333333}, {"themes": [0, 1, 0, 0, 0, 0, 0, 0, 0, 1, 0], "dialogues": [{"uttered": "u5881", "characterName": "KEVIN", "lineId": "L287855", "sentiment": -0.2, "text": "We can't carry all this.  It's too heavy."}, {"uttered": "u5874", "characterName": "DENNIS", "lineId": "L287856", "sentiment": 0.2, "text": "I've been carrying you our whole fuckin' lives."}], "sentiment": 0.0}, {"themes": [0, 0, 0, 0, 0, 0, 0, 0, 0, 0, 0], "dialogues": [{"uttered": "u5881", "characterName": "KEVIN", "lineId": "L288088", "sentiment": -0.6, "text": "We're fucked."}, {"uttered": "u5874", "characterName": "DENNIS", "lineId": "L288089", "sentiment": -0.1125, "text": "We're fucked until we think of a way out; then we're rich."}, {"uttered": "u5881", "characterName": "KEVIN", "lineId": "L288090", "sentiment": 0.0, "text": "There is no way out."}, {"uttered": "u5874", "characterName": "DENNIS", "lineId": "L288091", "sentiment": 0.0, "text": "For chrissake, <u>please</u>!  Help me celebrate!  I figured it out!"}, {"uttered": "u5881", "characterName": "KEVIN", "lineId": "L288092", "sentiment": 0.0, "text": "Celebrate what?  Going to prison?"}], "sentiment": -0.155859375}, {"themes": [0, 0, 0, 0, 0, 1, 1, 0, 0, 0, 0], "dialogues": [{"uttered": "u5874", "characterName": "DENNIS", "lineId": "L288170", "sentiment": 0.1, "text": "If we don't escape, we gotta get the word out about the cash.  That's how we'll stay alive."}, {"uttered": "u5881", "characterName": "KEVIN", "lineId": "L288171", "sentiment": 0.0, "text": "What are you talking about?"}, {"uttered": "u5874", "characterName": "DENNIS", "lineId": "L288172", "sentiment": 0.142857143, "text": "The only way he can keep the cash is if nobody knows about it.  He's gotta cap all three of us before they even read our rights.  He's probably planning it right now."}, {"uttered": "u5881", "characterName": "KEVIN", "lineId": "L288173", "sentiment": -0.6, "text": "That's crazy.  He's not going to kill us."}, {"uttered": "u5874", "characterName": "DENNIS", "lineId": "L288174", "sentiment": -0.8, "text": "Kevin, you're so fuckin' stupid..."}], "sentiment": -0.202857143}, {"themes": [0, 0, 0, 0, 0, 0, 0, 0, 0, 0, 0], "dialogues": [{"uttered": "u5881", "characterName": "KEVIN", "lineId": "L288175", "sentiment": 0.0, "text": "It's over.  We have to give up."}, {"uttered": "u5874", "characterName": "DENNIS", "lineId": "L288176", "sentiment": -0.4, "text": "Fuck it's over.  That money's mine."}, {"uttered": "u5881", "characterName": "KEVIN", "lineId": "L288177", "sentiment": -0.416666667, "text": "That money's fucked up your brain. Talley's going to get tired of waiting for us to give up, and we'll all be fuckin' killed!"}], "sentiment": -0.4125}, {"themes": [0, 0, 0, 0, 1, 0, 1, 0, 0, 0, 0], "dialogues": [{"uttered": "u5874", "characterName": "DENNIS", "lineId": "L288178", "sentiment": 0.375, "text": "Then we might as well die rich."}, {"uttered": "u5881", "characterName": "KEVIN", "lineId": "L288179", "sentiment": 0.0, "text": "I'm not going to die for this!"}], "sentiment": 0.46875}], "target": "u5881"}, {"source": "u5891", "counts": 3, "lines": [{"themes": [0, 1, 0, 1, 0, 0, 0, 0, 0, 0, 1], "dialogues": [{"uttered": "u5896", "characterName": "WALTER", "lineId": "L288147", "sentiment": 0.0, "text": "Where are my children?"}, {"uttered": "u5891", "characterName": "TALLEY", "lineId": "L288148", "sentiment": 0.0, "text": "They're still in the house."}], "sentiment": 0.0}, {"themes": [1, 1, 0, 1, 0, 1, 0, 0, 0, 1, 1], "dialogues": [{"uttered": "u5896", "characterName": "WALTER", "lineId": "L288153", "sentiment": 0.0, "text": "I don't know what you're talking about."}, {"uttered": "u5891", "characterName": "TALLEY", "lineId": "L288154", "sentiment": 0.0, "text": "He's going to kill you.  Don't you know that?  He can't take the chance that you'll talk."}], "sentiment": 0.0}, {"themes": [0, 0, 0, 0, 1, 1, 0, 1, 0, 0, 0], "dialogues": [{"uttered": "u5896", "characterName": "WALTER", "lineId": "L288305", "sentiment": 0.0, "text": "Did you find the disks?"}, {"uttered": "u5891", "characterName": "TALLEY", "lineId": "L288306", "sentiment": 0.0, "text": "Yes."}, {"uttered": "u5896", "characterName": "WALTER", "lineId": "L288307", "sentiment": 0.0, "text": "Then you have everything.  You can put them away."}, {"uttered": "u5891", "characterName": "TALLEY", "lineId": "L288308", "sentiment": -0.15, "text": "A man has my family.  Gold watch here. Dark tan."}, {"uttered": "u5896", "characterName": "WALTER", "lineId": "L288309", "sentiment": 0.0, "text": "That would be Glen Howell.  He was on his way for the disks."}, {"uttered": "u5891", "characterName": "TALLEY", "lineId": "L288310", "sentiment": 0.0, "text": "How do I reach him?"}], "sentiment": -0.15}], "target": "u5896"}, {"source": "u5874", "counts": 6, "lines": [{"themes": [0, 0, 0, 0, 0, 1, 0, 0, 0, 0, 0], "dialogues": [{"uttered": "u5896", "characterName": "WALTER", "lineId": "L287508", "sentiment": 0.285714286, "text": "Jen?  Are you all right?"}, {"uttered": "u5874", "characterName": "DENNIS", "lineId": "L287509", "sentiment": -0.25, "text": "She'll be dead if you don't put your ass in that chair!"}], "sentiment": 0.017857143}, {"themes": [0, 1, 0, 0, 0, 0, 0, 0, 0, 0, 1], "dialogues": [{"uttered": "u5896", "characterName": "WALTER", "lineId": "L287511", "sentiment": 0.0, "text": "Who sent you?"}, {"uttered": "u5874", "characterName": "DENNIS", "lineId": "L287512", "sentiment": 0.0, "text": "Don't go Rambo and you'll tell'm about this on the back nine.  I'm gonna tie you up, then we're gonna take your car."}], "sentiment": 0.0}, {"themes": [0, 0, 0, 0, 0, 0, 0, 0, 0, 0, 0], "dialogues": [{"uttered": "u5896", "characterName": "WALTER", "lineId": "L287513", "sentiment": 0.0, "text": "The car.  All you want is the car?"}, {"uttered": "u5874", "characterName": "DENNIS", "lineId": "L287514", "sentiment": 0.0, "text": "Am I talkin' raghead?!  I want your car! <u>Gimme the goddamned keys</u>!"}], "sentiment": 0.0}, {"themes": [0, 0, 0, 0, 0, 0, 0, 0, 0, 0, 0], "dialogues": [{"uttered": "u5874", "characterName": "DENNIS", "lineId": "L287589", "sentiment": -0.243055556, "text": "Stay down!  Stay <u>down</u>, goddamnit!"}, {"uttered": "u5896", "characterName": "WALTER", "lineId": "L287590", "sentiment": 0.0, "text": "I'm going to my desk."}, {"uttered": "u5874", "characterName": "DENNIS", "lineId": "L287591", "sentiment": 0.0, "text": "You're not goin' anywhere!  Get on the fuckin' floor!"}], "sentiment": -0.379774306}, {"themes": [0, 1, 0, 0, 0, 0, 0, 0, 0, 0, 1], "dialogues": [{"uttered": "u5874", "characterName": "DENNIS", "lineId": "L287594", "sentiment": 0.0, "text": "<u>Get on the floor</u>!"}, {"uttered": "u5896", "characterName": "WALTER", "lineId": "L287595", "sentiment": 0.0, "text": "I have contacts in Los Angeles.  Lawyers and judges who can help you."}], "sentiment": 0.0}, {"themes": [0, 1, 0, 0, 0, 0, 1, 0, 0, 0, 1], "dialogues": [{"uttered": "u5874", "characterName": "DENNIS", "lineId": "L287600", "sentiment": 0.0, "text": "Mars, watch the cops!  Kevin!  Watch the back of the house!"}, {"uttered": "u5896", "characterName": "WALTER", "lineId": "L287601", "sentiment": 0.0, "text": "You won't die if you let me help."}, {"uttered": "u5874", "characterName": "DENNIS", "lineId": "L287602", "sentiment": 0.0, "text": "Bullshit!"}, {"uttered": "u5896", "characterName": "WALTER", "lineId": "L287603", "sentiment": 0.0, "text": "But if you stay in this house, I can promise you this --"}, {"uttered": "u5874", "characterName": "DENNIS", "lineId": "L287604", "sentiment": 0.0, "text": "<u>Shut up!  Shut up and get on the floor</u>!"}, {"uttered": "u5896", "characterName": "WALTER", "lineId": "L287605", "sentiment": -0.6, "text": "You can't imagine the fucking you're going to get."}], "sentiment": -0.3}], "target": "u5896"}, {"source": "u5887", "counts": 10, "lines": [{"themes": [0, 0, 0, 0, 1, 0, 1, 0, 0, 0, 0], "dialogues": [{"uttered": "u5891", "characterName": "TALLEY", "lineId": "L287835", "sentiment": 0.0, "text": "I'm Talley.  Who's in charge?"}, {"uttered": "u5887", "characterName": "MARTIN", "lineId": "L287836", "sentiment": 0.4, "text": "Laura Martin.  This is Will Maddox, the primary negotiator --"}], "sentiment": 0.4}, {"themes": [0, 0, 0, 0, 0, 1, 0, 0, 0, 0, 0], "dialogues": [{"uttered": "u5887", "characterName": "MARTIN", "lineId": "L287840", "sentiment": 0.0, "text": "Do it."}, {"uttered": "u5891", "characterName": "TALLEY", "lineId": "L287841", "sentiment": 0.0, "text": "Don't crowd the house.  The alpha's a kid named Rooney.  He's amped up and volatile."}], "sentiment": 0.0}, {"themes": [0, 0, 0, 0, 0, 0, 0, 0, 0, 0, 0], "dialogues": [{"uttered": "u5887", "characterName": "MARTIN", "lineId": "L287842", "sentiment": 0.0, "text": "Sounds like you know the job."}, {"uttered": "u5891", "characterName": "TALLEY", "lineId": "L287843", "sentiment": -0.291666667, "text": "I've done it once or twice.  I blocked their phones to incoming calls, so you'll have to cut in a hard line to talk to him."}, {"uttered": "u5887", "characterName": "MARTIN", "lineId": "L287844", "sentiment": 0.0, "text": "Maddox!  You got that?"}], "sentiment": -0.364583333}, {"themes": [0, 1, 0, 0, 0, 0, 0, 0, 0, 1, 0], "dialogues": [{"uttered": "u5891", "characterName": "TALLEY", "lineId": "L287869", "sentiment": 0.0, "text": "Then get your men off the wall!  You breach that house, we're gonna have a bloodbath!  I <u>know</u> this guy, Captain -- I can talk to him."}, {"uttered": "u5887", "characterName": "MARTIN", "lineId": "L287870", "sentiment": -0.155555556, "text": "Order your men to stand down."}], "sentiment": -0.155555556}, {"themes": [0, 1, 0, 0, 0, 0, 0, 0, 0, 1, 0], "dialogues": [{"uttered": "u5891", "characterName": "TALLEY", "lineId": "L287889", "sentiment": 0.0, "text": "He says he has gasoline set to burn the place."}, {"uttered": "u5887", "characterName": "MARTIN", "lineId": "L287890", "sentiment": 0.0, "text": "Jesus.  He must've siphoned it from the cars."}, {"uttered": "u5891", "characterName": "TALLEY", "lineId": "L287891", "sentiment": 0.2, "text": "If you go in, you can't use tear gas or flashbangs.  The whole place would go up."}, {"uttered": "u5887", "characterName": "MARTIN", "lineId": "L287892", "sentiment": 0.285714286, "text": "Looks like you're bailing out at the right time."}, {"uttered": "u5891", "characterName": "TALLEY", "lineId": "L287893", "sentiment": 0.0, "text": "That's why you get the big bucks, Captain."}], "sentiment": 0.161904762}, {"themes": [0, 1, 0, 0, 0, 1, 0, 0, 0, 1, 0], "dialogues": [{"uttered": "u5891", "characterName": "TALLEY", "lineId": "L287933", "sentiment": 0.0, "text": "He says that his father's hurt."}, {"uttered": "u5887", "characterName": "MARTIN", "lineId": "L287934", "sentiment": 0.0, "text": "If we have a man dying in there, we'll have to go in."}, {"uttered": "u5891", "characterName": "TALLEY", "lineId": "L287935", "sentiment": 0.0, "text": "They have security cameras.  Rooney would see you coming."}, {"uttered": "u5887", "characterName": "MARTIN", "lineId": "L287936", "sentiment": 0.0, "text": "Did the boy say that any of them are in immediate danger?"}, {"uttered": "u5891", "characterName": "TALLEY", "lineId": "L287937", "sentiment": 0.0, "text": "No.  He said that his father's unconscious; he didn't say he was dying."}, {"uttered": "u5887", "characterName": "MARTIN", "lineId": "L287938", "sentiment": 0.0, "text": "Then I think we should wait.  Do you agree?"}], "sentiment": 0.0}, {"themes": [0, 0, 0, 0, 1, 0, 1, 1, 1, 0, 0], "dialogues": [{"uttered": "u5891", "characterName": "TALLEY", "lineId": "L287939", "sentiment": 0.0, "text": "You want me to stick around, I could --"}, {"uttered": "u5887", "characterName": "MARTIN", "lineId": "L287940", "sentiment": 0.0, "text": "You've been here all day, Chief.  Take a break.  See your family.  If I need you, I'll call."}], "sentiment": 0.0}, {"themes": [0, 0, 0, 0, 0, 0, 1, 0, 1, 0, 0], "dialogues": [{"uttered": "u5887", "characterName": "MARTIN", "lineId": "L287984", "sentiment": -0.05, "text": "Excuse me?  <u>You</u> requested our help.  You turned over command --"}, {"uttered": "u5891", "characterName": "TALLEY", "lineId": "L287985", "sentiment": 0.0, "text": "And now I'm taking it back.  We're getting Smith out of the house."}], "sentiment": -0.025}, {"themes": [0, 1, 1, 0, 0, 0, 0, 0, 1, 1, 0], "dialogues": [{"uttered": "u5887", "characterName": "MARTIN", "lineId": "L288080", "sentiment": 0.0, "text": "I want to know what in hell you're doing."}, {"uttered": "u5891", "characterName": "TALLEY", "lineId": "L288081", "sentiment": 0.0, "text": "I'm looking for you.  I need your tactical unit."}, {"uttered": "u5887", "characterName": "MARTIN", "lineId": "L288082", "sentiment": -0.02, "text": "I'm not stupid!  You can't get out of here fast enough, then you take back command; you agree to wait on Smith, then you risk everything in a stupid stunt to get him out --"}, {"uttered": "u5891", "characterName": "TALLEY", "lineId": "L288083", "sentiment": 0.0, "text": "Don't question me, Captain!  This is <u>my</u> crime scene!"}, {"uttered": "u5887", "characterName": "MARTIN", "lineId": "L288084", "sentiment": 0.125, "text": "-- then when you get him, you damn near assault the man in the ambulance!  <u>What</u> <u>is going on</u>?"}], "sentiment": -0.029166667}, {"themes": [0, 0, 0, 0, 0, 1, 0, 0, 0, 0, 0], "dialogues": [{"uttered": "u5891", "characterName": "TALLEY", "lineId": "L288235", "sentiment": 0.0, "text": "Let it go, Captain."}, {"uttered": "u5887", "characterName": "MARTIN", "lineId": "L288236", "sentiment": -0.25, "text": "Goddamned small town bullshit."}], "sentiment": -0.25}], "target": "u5891"}, {"source": "u5874", "counts": 15, "lines": [{"themes": [0, 0, 0, 0, 0, 0, 0, 0, 1, 0, 0], "dialogues": [{"uttered": "u5874", "characterName": "DENNIS", "lineId": "L287638", "sentiment": 0.0, "text": "You with the cops?"}, {"uttered": "u5891", "characterName": "TALLEY", "lineId": "L287639", "sentiment": 0.0, "text": "The Bristo Police Department.  Look out the window.  You see the car?"}], "sentiment": 0.0}, {"themes": [0, 0, 0, 0, 0, 0, 0, 0, 0, 0, 0], "dialogues": [{"uttered": "u5874", "characterName": "DENNIS", "lineId": "L287640", "sentiment": 0.0, "text": "Yeah.  I'm Rooney."}, {"uttered": "u5891", "characterName": "TALLEY", "lineId": "L287641", "sentiment": -1.0, "text": "We had an awful lot of shooting.  You need a doctor in there?"}], "sentiment": -1.0}, {"themes": [0, 0, 1, 0, 0, 0, 0, 1, 0, 1, 0], "dialogues": [{"uttered": "u5874", "characterName": "DENNIS", "lineId": "L287642", "sentiment": 0.35, "text": "We're cool."}, {"uttered": "u5891", "characterName": "TALLEY", "lineId": "L287643", "sentiment": 0.0, "text": "Let me speak to Mr. Smith.  I want to hear it from him."}, {"uttered": "u5874", "characterName": "DENNIS", "lineId": "L287644", "sentiment": -0.3, "text": "Fuck you.  I'm running this shit.  You talk to me."}, {"uttered": "u5891", "characterName": "TALLEY", "lineId": "L287645", "sentiment": 0.0, "text": "How about your two friends?  You don't have a man dying in there, do you?"}, {"uttered": "u5874", "characterName": "DENNIS", "lineId": "L287646", "sentiment": 0.416666667, "text": "They're fine."}], "sentiment": 0.041666667}, {"themes": [0, 1, 0, 0, 0, 1, 1, 0, 1, 1, 1], "dialogues": [{"uttered": "u5891", "characterName": "TALLEY", "lineId": "L287647", "sentiment": 0.45, "text": "All three subjects are confirmed inside. Call off the house-to-house.  Okay, Dennis, I want to explain your situation --"}, {"uttered": "u5874", "characterName": "DENNIS", "lineId": "L287648", "sentiment": -0.25, "text": "You don't have to explain shit!  That Chinaman pulled a gun.  We wrestled for it.  That Chinaman shot himself."}, {"uttered": "u5891", "characterName": "TALLEY", "lineId": "L287649", "sentiment": 0.0, "text": "Mr. Kim didn't make it, Dennis.  He died."}, {"uttered": "u5874", "characterName": "DENNIS", "lineId": "L287650", "sentiment": 0.0, "text": "How about the cop?"}, {"uttered": "u5891", "characterName": "TALLEY", "lineId": "L287651", "sentiment": 0.0, "text": "Dennis?  I want you to release those people."}, {"uttered": "u5874", "characterName": "DENNIS", "lineId": "L287652", "sentiment": -0.2, "text": "Fuck that.  They're the only thing stopping you from blowing us away."}, {"uttered": "u5891", "characterName": "TALLEY", "lineId": "L287653", "sentiment": 0.35, "text": "We're not coming in there by force, okay? No one wants to hurt you."}, {"uttered": "u5874", "characterName": "DENNIS", "lineId": "L287654", "sentiment": 0.0, "text": "I got these people!  You try to come get me, I'll kill every fuckin' one of them!"}], "sentiment": 0.151785714}, {"themes": [1, 1, 0, 0, 0, 0, 0, 0, 0, 0, 0], "dialogues": [{"uttered": "u5891", "characterName": "TALLEY", "lineId": "L287873", "sentiment": 0.0, "text": "It's over now, Dennis!  Don't hurt anyone."}, {"uttered": "u5874", "characterName": "DENNIS", "lineId": "L287874", "sentiment": -0.243055556, "text": "We'll burn this fuckin' place down!  I got gasoline all over in here!"}], "sentiment": -0.243055556}, {"themes": [0, 1, 0, 0, 1, 0, 1, 0, 0, 1, 1], "dialogues": [{"uttered": "u5874", "characterName": "DENNIS", "lineId": "L287878", "sentiment": 0.0, "text": "Talley?"}, {"uttered": "u5891", "characterName": "TALLEY", "lineId": "L287879", "sentiment": 0.0, "text": "I'm here."}, {"uttered": "u5874", "characterName": "DENNIS", "lineId": "L287880", "sentiment": 0.0, "text": "I want a helicopter to take us to Mexico."}, {"uttered": "u5891", "characterName": "TALLEY", "lineId": "L287881", "sentiment": 0.0, "text": "That's not going to happen, Dennis.  They won't give you a helicopter."}, {"uttered": "u5874", "characterName": "DENNIS", "lineId": "L287882", "sentiment": 0.0, "text": "I'll give you these people."}, {"uttered": "u5891", "characterName": "TALLEY", "lineId": "L287883", "sentiment": 0.187142857, "text": "The Mexican police would arrest you as soon as it landed.  There's only one way out and you're doing it right now--just keep talking to us.  I think we could make the transition now. Maddox, you good to go?"}], "sentiment": 0.187142857}, {"themes": [0, 0, 0, 0, 0, 0, 0, 0, 0, 0, 0], "dialogues": [{"uttered": "u5891", "characterName": "TALLEY", "lineId": "L287884", "sentiment": -0.2, "text": "Hey, Dennis?  Can I let you in on a personal secret?"}, {"uttered": "u5874", "characterName": "DENNIS", "lineId": "L287885", "sentiment": 0.0, "text": "What?"}, {"uttered": "u5891", "characterName": "TALLEY", "lineId": "L287886", "sentiment": -1.0, "text": "I gotta piss real bad."}], "sentiment": -0.466666667}, {"themes": [0, 0, 0, 0, 0, 0, 0, 0, 1, 0, 0], "dialogues": [{"uttered": "u5874", "characterName": "DENNIS", "lineId": "L287887", "sentiment": 0.25, "text": "You're a funny guy, Talley."}, {"uttered": "u5891", "characterName": "TALLEY", "lineId": "L287888", "sentiment": 0.0, "text": "I'm going to put on an officer named Will Maddox.  You talk to him for a while."}], "sentiment": 0.25}, {"themes": [0, 0, 0, 0, 1, 0, 0, 0, 0, 0, 0], "dialogues": [{"uttered": "u5874", "characterName": "DENNIS", "lineId": "L287998", "sentiment": 0.0, "text": "That you, Talley?"}, {"uttered": "u5891", "characterName": "TALLEY", "lineId": "L287999", "sentiment": -0.09375, "text": "The one and only.  We got a little problem out here, Dennis."}, {"uttered": "u5874", "characterName": "DENNIS", "lineId": "L288000", "sentiment": 0.0, "text": "You oughta try on the problem I got in here."}, {"uttered": "u5891", "characterName": "TALLEY", "lineId": "L288001", "sentiment": 0.0, "text": "I need you to let me talk to Mr. Smith."}], "sentiment": -0.09375}, {"themes": [0, 0, 0, 0, 0, 0, 0, 0, 0, 0, 0], "dialogues": [{"uttered": "u5874", "characterName": "DENNIS", "lineId": "L288002", "sentiment": 0.0, "text": "We been through that.  Forget it."}, {"uttered": "u5891", "characterName": "TALLEY", "lineId": "L288003", "sentiment": -0.2, "text": "We can't forget it.  The Sheriffs think you won't let me talk to Smith because he's dead.  They think you murdered him."}], "sentiment": -0.2}, {"themes": [0, 0, 0, 0, 0, 1, 1, 0, 0, 0, 0], "dialogues": [{"uttered": "u5891", "characterName": "TALLEY", "lineId": "L288013", "sentiment": 0.0, "text": "Now I understand.  That helps.  I can make them understand that."}, {"uttered": "u5874", "characterName": "DENNIS", "lineId": "L288014", "sentiment": 0.5, "text": "Okay."}, {"uttered": "u5891", "characterName": "TALLEY", "lineId": "L288015", "sentiment": 0.0, "text": "Let me come get him."}, {"uttered": "u5874", "characterName": "DENNIS", "lineId": "L288016", "sentiment": -0.625, "text": "Fuck that!  You bastards will jump me!"}, {"uttered": "u5891", "characterName": "TALLEY", "lineId": "L288017", "sentiment": 0.0, "text": "If you won't let me come in, then put him outside."}, {"uttered": "u5874", "characterName": "DENNIS", "lineId": "L288018", "sentiment": 0.0, "text": "You'll cap my ass as soon as I step out the door!"}, {"uttered": "u5891", "characterName": "TALLEY", "lineId": "L288019", "sentiment": 0.214285714, "text": "You've already helped yourself once, Dennis; be smart again.  If you save his life, it'll help when you get to court."}], "sentiment": 0.022321429}, {"themes": [0, 0, 0, 0, 0, 0, 1, 0, 0, 0, 0], "dialogues": [{"uttered": "u5874", "characterName": "DENNIS", "lineId": "L288109", "sentiment": 0.0, "text": "You got a sniper out there, gonna shoot me?"}, {"uttered": "u5891", "characterName": "TALLEY", "lineId": "L288110", "sentiment": 0.0, "text": "Only if you try to grab me.  We could've shot you from the wall."}], "sentiment": 0.0}, {"themes": [0, 0, 0, 0, 0, 1, 0, 0, 0, 0, 0], "dialogues": [{"uttered": "u5891", "characterName": "TALLEY", "lineId": "L288111", "sentiment": -0.05, "text": "You've been in there a long time. What're you waiting for?"}, {"uttered": "u5874", "characterName": "DENNIS", "lineId": "L288112", "sentiment": 0.0, "text": "Would you be in a hurry to go to prison for the rest of your life?"}, {"uttered": "u5891", "characterName": "TALLEY", "lineId": "L288113", "sentiment": 1.0, "text": "I'd be trying to get the best deal that I could."}, {"uttered": "u5874", "characterName": "DENNIS", "lineId": "L288114", "sentiment": 0.0, "text": "Maybe that's what I'm doing.  Can I reach in my pocket, show you something?"}], "sentiment": 0.475}, {"themes": [0, 0, 0, 0, 1, 0, 0, 0, 0, 0, 0], "dialogues": [{"uttered": "u5891", "characterName": "TALLEY", "lineId": "L288117", "sentiment": -0.7, "text": "You picked a bad house to hole up in, son."}, {"uttered": "u5874", "characterName": "DENNIS", "lineId": "L288118", "sentiment": 0.285714286, "text": "Two hundred thousand cash, right in your pocket, no one needs to know."}, {"uttered": "u5891", "characterName": "TALLEY", "lineId": "L288119", "sentiment": 0.0, "text": "Give up."}, {"uttered": "u5874", "characterName": "DENNIS", "lineId": "L288120", "sentiment": -0.166666667, "text": "There's a million dollars in there, maybe <u>two</u> million.  I'll give you half."}], "sentiment": -0.193650794}, {"themes": [0, 0, 0, 0, 0, 0, 0, 0, 0, 0, 0], "dialogues": [{"uttered": "u5874", "characterName": "DENNIS", "lineId": "L288122", "sentiment": 0.7, "text": "It ain't been a good day, Chief."}, {"uttered": "u5891", "characterName": "TALLEY", "lineId": "L288123", "sentiment": -0.3, "text": "Give up, Dennis.  Let these people go. At least you'll have your life."}], "sentiment": 0.2}], "target": "u5891"}, {"source": "u5877", "counts": 9, "lines": [{"themes": [0, 0, 0, 0, 0, 1, 1, 0, 0, 0, 0], "dialogues": [{"uttered": "u5877", "characterName": "HOWELL", "lineId": "L288313", "sentiment": 0.0, "text": "How did you get this number?"}, {"uttered": "u5891", "characterName": "TALLEY", "lineId": "L288314", "sentiment": -0.141666667, "text": "Mr. Jones is dead.  So are two of his men.  The other three are in jail.  I have the disks.  I have Walter Smith. And you know what, you motherfucker?  I have you."}, {"uttered": "u5877", "characterName": "HOWELL", "lineId": "L288315", "sentiment": -0.6, "text": "I have your fucking family.  Don't forget that."}, {"uttered": "u5891", "characterName": "TALLEY", "lineId": "L288316", "sentiment": 0.0, "text": "I also have a couple of million in cash. Call Sonny Benza.  Ask if I can keep it."}], "sentiment": -0.25625}, {"themes": [1, 0, 0, 0, 0, 1, 1, 0, 0, 0, 0], "dialogues": [{"uttered": "u5877", "characterName": "HOWELL", "lineId": "L288317", "sentiment": 0.0, "text": "What do you want?"}, {"uttered": "u5891", "characterName": "TALLEY", "lineId": "L288318", "sentiment": 0.0, "text": "My wife and my daughter and the money. I'll bring the disks to the mall by the freeway, you bring my family.  We'll trade."}, {"uttered": "u5877", "characterName": "HOWELL", "lineId": "L288319", "sentiment": -0.625, "text": "Fuck that!  You think I'm crazy?!"}, {"uttered": "u5891", "characterName": "TALLEY", "lineId": "L288320", "sentiment": 0.0, "text": "I think you got no choice."}], "sentiment": -0.625}, {"themes": [0, 0, 0, 0, 0, 0, 0, 0, 0, 0, 0], "dialogues": [{"uttered": "u5877", "characterName": "HOWELL", "lineId": "L288321", "sentiment": -0.4, "text": "Fuck the mall.  You know that motel on the road west of town?"}, {"uttered": "u5891", "characterName": "TALLEY", "lineId": "L288322", "sentiment": 0.0, "text": "Yeah."}, {"uttered": "u5877", "characterName": "HOWELL", "lineId": "L288323", "sentiment": -0.15, "text": "You got ten minutes.  If you're one minute late, we won't be here to find."}], "sentiment": -0.233333333}, {"themes": [0, 0, 0, 0, 0, 0, 1, 0, 0, 0, 0], "dialogues": [{"uttered": "u5877", "characterName": "HOWELL", "lineId": "L288343", "sentiment": 0.433333333, "text": "Take it easy.  Just take it easy.  We're here to do business."}, {"uttered": "u5891", "characterName": "TALLEY", "lineId": "L288344", "sentiment": 0.0, "text": "You said they would be here, goddamnit! Where are they?"}], "sentiment": 0.4875}, {"themes": [0, 0, 0, 0, 0, 0, 1, 0, 0, 0, 0], "dialogues": [{"uttered": "u5877", "characterName": "HOWELL", "lineId": "L288345", "sentiment": 0.5, "text": "They're close.  Let me make a call.  You can see they're okay."}, {"uttered": "u5891", "characterName": "TALLEY", "lineId": "L288346", "sentiment": 0.0, "text": "You said they would be here!"}], "sentiment": 0.625}, {"themes": [0, 0, 0, 0, 1, 0, 0, 0, 0, 0, 0], "dialogues": [{"uttered": "u5891", "characterName": "TALLEY", "lineId": "L288351", "sentiment": -0.125, "text": "You get the other one when I have my girls.  Not <u>talk</u> to them; <u>have</u> them."}, {"uttered": "u5877", "characterName": "HOWELL", "lineId": "L288352", "sentiment": 0.0, "text": "Where is it?"}, {"uttered": "u5891", "characterName": "TALLEY", "lineId": "L288353", "sentiment": 0.0, "text": "Close."}], "sentiment": -0.125}, {"themes": [0, 0, 0, 0, 0, 0, 0, 0, 0, 0, 0], "dialogues": [{"uttered": "u5877", "characterName": "HOWELL", "lineId": "L288355", "sentiment": 0.142857143, "text": "All right.  Now the second one."}, {"uttered": "u5891", "characterName": "TALLEY", "lineId": "L288356", "sentiment": 0.0625, "text": "First my girls.  I get my girls, you get the other disk."}], "sentiment": 0.102678571}, {"themes": [0, 0, 1, 0, 0, 0, 0, 0, 0, 0, 0], "dialogues": [{"uttered": "u5891", "characterName": "TALLEY", "lineId": "L288359", "sentiment": -0.15625, "text": "I'll kill you!  You won't get the other disk!"}, {"uttered": "u5877", "characterName": "HOWELL", "lineId": "L288360", "sentiment": 0.0, "text": "If you shoot me, he'll kill your daughter.  Do you want to lose both of them?"}], "sentiment": -0.15625}, {"themes": [0, 0, 0, 0, 1, 0, 0, 0, 0, 0, 0], "dialogues": [{"uttered": "u5891", "characterName": "TALLEY", "lineId": "L288363", "sentiment": -0.3125, "text": "I gave the other one to the Sheriffs and they're giving it to the <u>real</u> FBI.  This one's a fake."}, {"uttered": "u5877", "characterName": "HOWELL", "lineId": "L288364", "sentiment": 0.5, "text": "You'd better be kidding."}], "sentiment": -0.041666667}], "target": "u5891"}, {"source": "u5874", "counts": 8, "lines": [{"themes": [0, 1, 0, 1, 1, 0, 0, 0, 0, 0, 1], "dialogues": [{"uttered": "u5886", "characterName": "MARS", "lineId": "L287777", "sentiment": 0.0, "text": "It's a safety room.  If anyone breaks into your house, you can hide."}, {"uttered": "u5874", "characterName": "DENNIS", "lineId": "L287778", "sentiment": 0.0625, "text": "Who gives a shit, Mars?  Check out the cash!  We're rich."}, {"uttered": "u5886", "characterName": "MARS", "lineId": "L287779", "sentiment": -0.2, "text": "We're trapped in a house."}], "sentiment": -0.025}, {"themes": [0, 1, 0, 1, 0, 0, 0, 0, 0, 0, 1], "dialogues": [{"uttered": "u5874", "characterName": "DENNIS", "lineId": "L287780", "sentiment": 0.0, "text": "We can take it with us."}, {"uttered": "u5886", "characterName": "MARS", "lineId": "L287781", "sentiment": 0.0, "text": "You can't run with suitcases."}], "sentiment": 0.0}, {"themes": [0, 0, 0, 0, 0, 0, 0, 0, 0, 0, 0], "dialogues": [{"uttered": "u5874", "characterName": "DENNIS", "lineId": "L287795", "sentiment": 0.492857143, "text": "That's right.  That's a good idea, Mars."}, {"uttered": "u5886", "characterName": "MARS", "lineId": "L287796", "sentiment": -0.178571429, "text": "Find something:  Extension cords, rope, wire--we'll have to tie them tight."}, {"uttered": "u5874", "characterName": "DENNIS", "lineId": "L287797", "sentiment": 0.0, "text": "Find something, Kevin.  Don't just stand there.  And tie this bastard, too.  I don't want him waking up and goin' Rambo on us."}], "sentiment": 0.269047619}, {"themes": [0, 1, 0, 1, 0, 0, 0, 0, 0, 1, 1], "dialogues": [{"uttered": "u5874", "characterName": "DENNIS", "lineId": "L287860", "sentiment": 0.0, "text": "The cops are comin'!"}, {"uttered": "u5886", "characterName": "MARS", "lineId": "L287861", "sentiment": 0.0, "text": "I got the gasoline --"}, {"uttered": "u5874", "characterName": "DENNIS", "lineId": "L287862", "sentiment": 0.0, "text": "We don't have time!"}], "sentiment": 0.0}, {"themes": [0, 0, 0, 0, 1, 0, 0, 0, 0, 0, 0], "dialogues": [{"uttered": "u5874", "characterName": "DENNIS", "lineId": "L287901", "sentiment": -0.4, "text": "What the fuck is that?"}, {"uttered": "u5886", "characterName": "MARS", "lineId": "L287902", "sentiment": 0.0, "text": "They'll cut the power."}], "sentiment": -0.4}, {"themes": [0, 1, 0, 0, 0, 0, 0, 0, 0, 0, 1], "dialogues": [{"uttered": "u5874", "characterName": "DENNIS", "lineId": "L288094", "sentiment": 0.2875, "text": "Cops want to be rich like everyone else. All we have to do is share.  And if he wants someone to swing for the Chinaman, we'll give'm Mars."}, {"uttered": "u5886", "characterName": "MARS", "lineId": "L288095", "sentiment": 0.0, "text": "Dennis."}], "sentiment": 0.2875}, {"themes": [0, 0, 1, 0, 0, 0, 0, 0, 0, 0, 0], "dialogues": [{"uttered": "u5874", "characterName": "DENNIS", "lineId": "L288182", "sentiment": 0.0, "text": "You got something to say?"}, {"uttered": "u5886", "characterName": "MARS", "lineId": "L288183", "sentiment": 0.0, "text": "I like it here, Dennis.  I'm never going to leave."}, {"uttered": "u5874", "characterName": "DENNIS", "lineId": "L288184", "sentiment": 0.0, "text": "Fuckin' A."}], "sentiment": 0.0}, {"themes": [0, 0, 0, 0, 1, 1, 1, 0, 0, 0, 0], "dialogues": [{"uttered": "u5874", "characterName": "DENNIS", "lineId": "L288248", "sentiment": -0.3125, "text": "You mean he <u>left</u>, as in went out the front door?"}, {"uttered": "u5886", "characterName": "MARS", "lineId": "L288249", "sentiment": 0.0, "text": "I overheard him with the girl."}, {"uttered": "u5874", "characterName": "DENNIS", "lineId": "L288250", "sentiment": 0.0, "text": "<u>Shit</u>!  That <u>fuck</u>!  Even when I want to turn myself in he screws it up!  Did he take the kids with him?"}, {"uttered": "u5886", "characterName": "MARS", "lineId": "L288251", "sentiment": 0.0, "text": "I don't know."}, {"uttered": "u5874", "characterName": "DENNIS", "lineId": "L288252", "sentiment": -0.75, "text": "Jesus, get upstairs and find out!  If he took those kids, we're fucked!"}], "sentiment": -0.756469727}], "target": "u5886"}], "movieId": "m389", "female": [{"gender": "f", "cname": "JENNIFER", "id": "u5879"}, {"gender": "f", "cname": "LOUISE", "id": "u5883"}], "year": "2005/I", "femaleLinks": [], "crossGenderLinks": [{"source": "u5874", "counts": 4, "lines": [{"themes": [0, 0, 0, 0, 0, 0, 0, 0, 0, 0, 0], "dialogues": [{"uttered": "u5874", "characterName": "DENNIS", "lineId": "L287505", "sentiment": 0.0, "text": "Who else is here?"}, {"uttered": "u5879", "characterName": "JENNIFER", "lineId": "L287506", "sentiment": 0.0, "text": "My father."}], "sentiment": 0.0}, {"themes": [0, 0, 0, 0, 1, 0, 0, 0, 0, 0, 0], "dialogues": [{"uttered": "u5879", "characterName": "JENNIFER", "lineId": "L287623", "sentiment": 0.0, "text": "He needs a doctor."}, {"uttered": "u5874", "characterName": "DENNIS", "lineId": "L287624", "sentiment": -0.155555556, "text": "Shut up and sit down.  You think someone's gonna make a house call?"}], "sentiment": -0.155555556}, {"themes": [0, 0, 0, 0, 1, 0, 1, 0, 0, 0, 0], "dialogues": [{"uttered": "u5879", "characterName": "JENNIFER", "lineId": "L287787", "sentiment": 0.0, "text": "My father needs a doctor.  <u>Please</u>."}, {"uttered": "u5874", "characterName": "DENNIS", "lineId": "L287788", "sentiment": 0.0, "text": "Hey, I've got a situation here, in case you haven't noticed."}, {"uttered": "u5879", "characterName": "JENNIFER", "lineId": "L287789", "sentiment": 0.0, "text": "All you're doing is watching yourself on TV.  <u>Look</u> at him."}, {"uttered": "u5874", "characterName": "DENNIS", "lineId": "L287790", "sentiment": 0.5, "text": "Use more ice."}, {"uttered": "u5879", "characterName": "JENNIFER", "lineId": "L287791", "sentiment": 0.0, "text": "I'm getting a doctor!"}], "sentiment": 0.625}, {"themes": [0, 0, 0, 0, 0, 0, 1, 0, 0, 0, 0], "dialogues": [{"uttered": "u5879", "characterName": "JENNIFER", "lineId": "L287903", "sentiment": 0.0, "text": "What about my father?"}, {"uttered": "u5874", "characterName": "DENNIS", "lineId": "L287904", "sentiment": -0.25, "text": "Aw, Jesus, not more of this."}, {"uttered": "u5879", "characterName": "JENNIFER", "lineId": "L287905", "sentiment": 0.0, "text": "<u>Look</u> at him!  I think he's dying!"}, {"uttered": "u5874", "characterName": "DENNIS", "lineId": "L287906", "sentiment": -0.195833333, "text": "Take'm back upstairs, but don't tie'm like before.  That little fuck untied himself anyway."}], "sentiment": -0.24453125}], "target": "u5879"}, {"source": "u5886", "counts": 7, "lines": [{"themes": [0, 0, 0, 0, 1, 0, 0, 0, 0, 0, 0], "dialogues": [{"uttered": "u5886", "characterName": "MARS", "lineId": "L287632", "sentiment": 0.0, "text": "Want one?"}, {"uttered": "u5879", "characterName": "JENNIFER", "lineId": "L287633", "sentiment": 0.0, "text": "I don't drink beer."}, {"uttered": "u5886", "characterName": "MARS", "lineId": "L287634", "sentiment": 0.285714286, "text": "Mommy won't know.  You can do anything you want right now.  Mommy won't know."}, {"uttered": "u5879", "characterName": "JENNIFER", "lineId": "L287635", "sentiment": 0.0, "text": "What I want is to help my father."}], "sentiment": 0.285714286}, {"themes": [0, 0, 0, 0, 0, 0, 0, 0, 0, 0, 0], "dialogues": [{"uttered": "u5879", "characterName": "JENNIFER", "lineId": "L287988", "sentiment": 0.0, "text": "What do you want?"}, {"uttered": "u5886", "characterName": "MARS", "lineId": "L287989", "sentiment": 0.0, "text": "We can't make the microwave work."}], "sentiment": 0.0}, {"themes": [0, 0, 1, 0, 0, 0, 0, 0, 0, 0, 0], "dialogues": [{"uttered": "u5879", "characterName": "JENNIFER", "lineId": "L287990", "sentiment": 0.0, "text": "What?"}, {"uttered": "u5886", "characterName": "MARS", "lineId": "L287991", "sentiment": 0.0, "text": "We're hungry.  You're going to cook."}], "sentiment": 0.0}, {"themes": [0, 1, 0, 0, 1, 0, 1, 0, 1, 1, 0], "dialogues": [{"uttered": "u5886", "characterName": "MARS", "lineId": "L287992", "sentiment": 0.25, "text": "Make the pizza.  I want scrambled eggs and hot dogs on mine."}, {"uttered": "u5879", "characterName": "JENNIFER", "lineId": "L287993", "sentiment": -0.2, "text": "How about dog shit?"}], "sentiment": 0.025}, {"themes": [0, 0, 0, 0, 1, 0, 0, 0, 0, 0, 0], "dialogues": [{"uttered": "u5886", "characterName": "MARS", "lineId": "L288254", "sentiment": 0.0, "text": "Kevin left without you."}, {"uttered": "u5879", "characterName": "JENNIFER", "lineId": "L288255", "sentiment": 0.0, "text": "I don't know what you're talking about."}], "sentiment": 0.0}, {"themes": [0, 1, 0, 1, 0, 0, 0, 0, 0, 1, 1], "dialogues": [{"uttered": "u5879", "characterName": "JENNIFER", "lineId": "L288257", "sentiment": 0.3125, "text": "You'd better get out of here!  Kevin's coming back!"}, {"uttered": "u5886", "characterName": "MARS", "lineId": "L288258", "sentiment": 0.0, "text": "Kevin's gone, your daddy's gone, everybody's gone."}], "sentiment": 0.3125}, {"themes": [0, 1, 0, 1, 0, 0, 1, 0, 0, 0, 1], "dialogues": [{"uttered": "u5886", "characterName": "MARS", "lineId": "L288259", "sentiment": 0.0, "text": "Now we can do whatever we want."}, {"uttered": "u5879", "characterName": "JENNIFER", "lineId": "L288260", "sentiment": 0.0, "text": "Stop it."}], "sentiment": 0.0}], "target": "u5879"}, {"source": "u5894", "counts": 5, "lines": [{"themes": [0, 0, 0, 0, 0, 0, 0, 0, 0, 0, 0], "dialogues": [{"uttered": "u5879", "characterName": "JENNIFER", "lineId": "L287820", "sentiment": -0.25, "text": "Ow!  Shit!"}, {"uttered": "u5894", "characterName": "THOMAS", "lineId": "L287821", "sentiment": 0.0, "text": "Be quiet!  Listen!"}], "sentiment": -0.125}, {"themes": [0, 1, 0, 0, 0, 0, 1, 0, 0, 1, 1], "dialogues": [{"uttered": "u5879", "characterName": "JENNIFER", "lineId": "L287822", "sentiment": 0.0, "text": "No one's coming."}, {"uttered": "u5894", "characterName": "THOMAS", "lineId": "L287823", "sentiment": 0.0, "text": "That big asshole nailed my windows."}, {"uttered": "u5879", "characterName": "JENNIFER", "lineId": "L287824", "sentiment": 0.0, "text": "Mine, too."}, {"uttered": "u5894", "characterName": "THOMAS", "lineId": "L287825", "sentiment": 0.0, "text": "We can use the crawlspace to get downstairs.  Then we can run for it."}, {"uttered": "u5879", "characterName": "JENNIFER", "lineId": "L287826", "sentiment": 0.0, "text": "No!  I'm not going to leave Daddy with them!"}], "sentiment": 0.0}, {"themes": [0, 0, 0, 0, 0, 0, 0, 0, 0, 0, 0], "dialogues": [{"uttered": "u5894", "characterName": "THOMAS", "lineId": "L287827", "sentiment": 0.0, "text": "We can't carry him."}, {"uttered": "u5879", "characterName": "JENNIFER", "lineId": "L287828", "sentiment": 0.0, "text": "You go, Thomas.  You get out, and I'll stay with Daddy."}, {"uttered": "u5894", "characterName": "THOMAS", "lineId": "L287829", "sentiment": 0.0, "text": "I'm not gonna leave you!"}, {"uttered": "u5879", "characterName": "JENNIFER", "lineId": "L287830", "sentiment": 0.0, "text": "Go!  If you get out, maybe you can help the police!"}], "sentiment": 0.0}, {"themes": [0, 1, 0, 1, 0, 0, 0, 0, 0, 0, 1], "dialogues": [{"uttered": "u5879", "characterName": "JENNIFER", "lineId": "L287832", "sentiment": 0.0, "text": "You leave that gun alone!"}, {"uttered": "u5894", "characterName": "THOMAS", "lineId": "L287833", "sentiment": 0.0, "text": "Shh, they'll hear you!"}, {"uttered": "u5879", "characterName": "JENNIFER", "lineId": "L287834", "sentiment": 0.09375, "text": "Better than you getting killed!  Don't touch that gun!  Daddy says --"}], "sentiment": 0.09375}, {"themes": [0, 1, 0, 0, 0, 0, 0, 0, 0, 0, 0], "dialogues": [{"uttered": "u5879", "characterName": "JENNIFER", "lineId": "L288279", "sentiment": 0.5, "text": "He can't reach us in here.  We're safe."}, {"uttered": "u5894", "characterName": "THOMAS", "lineId": "L288280", "sentiment": 0.0, "text": "I know."}], "sentiment": 0.5}], "target": "u5879"}, {"source": "u5881", "counts": 5, "lines": [{"themes": [0, 0, 0, 0, 0, 0, 0, 0, 0, 0, 0], "dialogues": [{"uttered": "u5879", "characterName": "JENNIFER", "lineId": "L287629", "sentiment": 0.0, "text": "Please get away from me."}, {"uttered": "u5881", "characterName": "KEVIN", "lineId": "L287630", "sentiment": 0.0, "text": "Mars?  What are you doing?"}], "sentiment": 0.0}, {"themes": [0, 0, 0, 0, 0, 0, 0, 1, 0, 0, 0], "dialogues": [{"uttered": "u5881", "characterName": "KEVIN", "lineId": "L287800", "sentiment": 0.0, "text": "You gotta pee?"}, {"uttered": "u5879", "characterName": "JENNIFER", "lineId": "L287801", "sentiment": 0.0, "text": "I don't see why you can't just lock me in.  It's not like I can go anywhere."}, {"uttered": "u5881", "characterName": "KEVIN", "lineId": "L287802", "sentiment": 0.0, "text": "Either I'm going to tie you or Mars will tie you.  Which do you want?"}], "sentiment": 0.0}, {"themes": [0, 0, 0, 0, 0, 1, 1, 1, 0, 0, 0], "dialogues": [{"uttered": "u5879", "characterName": "JENNIFER", "lineId": "L287803", "sentiment": 0.2, "text": "Thanks for the shirt."}, {"uttered": "u5881", "characterName": "KEVIN", "lineId": "L287804", "sentiment": 0.0, "text": "Whatever."}, {"uttered": "u5879", "characterName": "JENNIFER", "lineId": "L287805", "sentiment": 0.0, "text": "Kevin, my father needs a doctor."}, {"uttered": "u5881", "characterName": "KEVIN", "lineId": "L287806", "sentiment": 0.0, "text": "He's just knocked out.  I've been knocked out."}, {"uttered": "u5879", "characterName": "JENNIFER", "lineId": "L287807", "sentiment": 0.0, "text": "If my father dies they'll charge you with his murder.  Can't you make Dennis see that?"}], "sentiment": 0.2}, {"themes": [0, 0, 0, 0, 0, 1, 0, 0, 0, 0, 0], "dialogues": [{"uttered": "u5879", "characterName": "JENNIFER", "lineId": "L288185", "sentiment": 0.0, "text": "What do you want?"}, {"uttered": "u5881", "characterName": "KEVIN", "lineId": "L288186", "sentiment": -0.155555556, "text": "Keep your voice down.  I'm taking you and your brother out of here."}], "sentiment": -0.155555556}, {"themes": [0, 0, 0, 0, 1, 0, 1, 0, 0, 0, 0], "dialogues": [{"uttered": "u5879", "characterName": "JENNIFER", "lineId": "L288187", "sentiment": 0.0, "text": "What happened?"}, {"uttered": "u5881", "characterName": "KEVIN", "lineId": "L288188", "sentiment": 0.0, "text": "Do you want to go or not?  I'm offering you a way out of here."}, {"uttered": "u5879", "characterName": "JENNIFER", "lineId": "L288189", "sentiment": 0.0, "text": "I can't go without Thomas."}, {"uttered": "u5881", "characterName": "KEVIN", "lineId": "L288190", "sentiment": 0.2, "text": "All three of us will go, but we have to move fast.  Mars and Dennis don't know I'm doing this."}, {"uttered": "u5879", "characterName": "JENNIFER", "lineId": "L288191", "sentiment": 0.0, "text": "How can we get out?"}, {"uttered": "u5881", "characterName": "KEVIN", "lineId": "L288192", "sentiment": -0.077777778, "text": "Dennis and Mars are in the den.  I'll get your brother, then come back for you. We'll go down the stairs and out the front door, you understand?"}, {"uttered": "u5879", "characterName": "JENNIFER", "lineId": "L288193", "sentiment": 0.0, "text": "Yes."}], "sentiment": 0.014814815}], "target": "u5879"}, {"source": "u5891", "counts": 3, "lines": [{"themes": [0, 0, 0, 0, 0, 0, 0, 0, 0, 0, 0], "dialogues": [{"uttered": "u5891", "characterName": "TALLEY", "lineId": "L287541", "sentiment": 0.0, "text": "What are you talking about, shot?  What happened?"}, {"uttered": "u5883", "characterName": "LOUISE", "lineId": "L287542", "sentiment": 0.0, "text": "Three white males shot Junior.  Mike followed them to York Estates --"}, {"uttered": "u5891", "characterName": "TALLEY", "lineId": "L287543", "sentiment": 0.0, "text": "Where are they?"}, {"uttered": "u5883", "characterName": "LOUISE", "lineId": "L287544", "sentiment": 0.0, "text": "York Estates.  Four-five-five Castle Way. Anders and Jorgenson are on the way."}], "sentiment": 0.0}, {"themes": [0, 0, 0, 0, 0, 0, 0, 0, 0, 0, 0], "dialogues": [{"uttered": "u5891", "characterName": "TALLEY", "lineId": "L287578", "sentiment": 0.0, "text": "That's not enough."}, {"uttered": "u5883", "characterName": "LOUISE", "lineId": "L287579", "sentiment": 0.0, "text": "What's that, Chief?  Say again."}, {"uttered": "u5891", "characterName": "TALLEY", "lineId": "L287580", "sentiment": 0.0, "text": "Get everyone out here.  Then call the Sheriffs.  Tell them we have a possible hostage situation."}], "sentiment": 0.0}, {"themes": [0, 1, 0, 0, 1, 0, 0, 0, 0, 1, 0], "dialogues": [{"uttered": "u5891", "characterName": "TALLEY", "lineId": "L287913", "sentiment": -0.5, "text": "Is something wrong with Jane?"}, {"uttered": "u5883", "characterName": "LOUISE", "lineId": "L287914", "sentiment": 0.0, "text": "We have a boy on the line.  He says he's Thomas Smith and he's calling from the house."}, {"uttered": "u5891", "characterName": "TALLEY", "lineId": "L287915", "sentiment": -0.25, "text": "It's a crank, Louise.  C'mon, don't waste my time with that!"}, {"uttered": "u5883", "characterName": "LOUISE", "lineId": "L287916", "sentiment": 0.2, "text": "His cell number belongs to the Smiths.  I think it's real, Chief.  I think this boy is inside that house."}], "sentiment": -0.183333333}], "target": "u5883"}], "male": [{"gender": "m", "cname": "ANDERS", "id": "u5869"}, {"gender": "m", "cname": "DENNIS", "id": "u5874"}, {"gender": "m", "cname": "HOWELL", "id": "u5877"}, {"gender": "m", "cname": "JANE", "id": "u5878"}, {"gender": "m", "cname": "KEVIN", "id": "u5881"}, {"gender": "m", "cname": "KLAUS", "id": "u5882"}, {"gender": "m", "cname": "MARS", "id": "u5886"}, {"gender": "m", "cname": "MARTIN", "id": "u5887"}, {"gender": "m", "cname": "TALLEY", "id": "u5891"}, {"gender": "m", "cname": "THOMAS", "id": "u5894"}, {"gender": "m", "cname": "WALTER", "id": "u5896"}], "movieTitle": "hostage"}